{"type":"FeatureCollection","features":[{"type":"Feature","properties":{"nom":"Affieux","code":"19001","codeDepartement":"19","codeRegion":"75","codesPostaux":["19260"],"population":364},"geometry":{"type":"Point","coordinates":[1.7682211013431002,45.50168171062274]}},{"type":"Feature","properties":{"nom":"Aix","code":"19002","codeDepartement":"19","codeRegion":"75","codesPostaux":["19200"],"population":389},"geometry":{"type":"Point","coordinates":[2.3909872088772857,45.616295334203635]}},{"type":"Feature","properties":{"nom":"Albignac","code":"19003","codeDepartement":"19","codeRegion":"75","codesPostaux":["19190"],"population":254},"geometry":{"type":"Point","coordinates":[1.6782444613402054,45.1460454587629]}},{"type":"Feature","properties":{"nom":"Albussac","code":"19004","codeDepartement":"19","codeRegion":"75","codesPostaux":["19380"],"population":722},"geometry":{"type":"Point","coordinates":[1.815005600439078,45.14131069045006]}},{"type":"Feature","properties":{"nom":"Allassac","code":"19005","codeDepartement":"19","codeRegion":"75","codesPostaux":["19240"],"population":3903},"geometry":{"type":"Point","coordinates":[1.4606072888498696,45.249820876207174]}},{"type":"Feature","properties":{"nom":"Alleyrat","code":"19006","codeDepartement":"19","codeRegion":"75","codesPostaux":["19200"],"population":95},"geometry":{"type":"Point","coordinates":[2.219379240875915,45.55892439416053]}},{"type":"Feature","properties":{"nom":"Altillac","code":"19007","codeDepartement":"19","codeRegion":"75","codesPostaux":["19120"],"population":867},"geometry":{"type":"Point","coordinates":[1.8761776706081081,44.979458645270284]}},{"type":"Feature","properties":{"nom":"Ambrugeat","code":"19008","codeDepartement":"19","codeRegion":"75","codesPostaux":["19250"],"population":201},"geometry":{"type":"Point","coordinates":[2.094455298059966,45.52796173192242]}},{"type":"Feature","properties":{"nom":"Les Angles-sur-Corrèze","code":"19009","codeDepartement":"19","codeRegion":"75","codesPostaux":["19000"],"population":109},"geometry":{"type":"Point","coordinates":[1.8042239832635985,45.31144042677825]}},{"type":"Feature","properties":{"nom":"Argentat-sur-Dordogne","code":"19010","codeDepartement":"19","codeRegion":"75","codesPostaux":["19400","19320"],"population":3083},"geometry":{"type":"Point","coordinates":[1.940772106284655,45.124147783733825]}},{"type":"Feature","properties":{"nom":"Arnac-Pompadour","code":"19011","codeDepartement":"19","codeRegion":"75","codesPostaux":["19230"],"population":1129},"geometry":{"type":"Point","coordinates":[1.3642407628361841,45.41321532762839]}},{"type":"Feature","properties":{"nom":"Astaillac","code":"19012","codeDepartement":"19","codeRegion":"75","codesPostaux":["19120"],"population":232},"geometry":{"type":"Point","coordinates":[1.8265981988636355,44.952842110795466]}},{"type":"Feature","properties":{"nom":"Aubazines","code":"19013","codeDepartement":"19","codeRegion":"75","codesPostaux":["19190"],"population":911},"geometry":{"type":"Point","coordinates":[1.6872744981684975,45.18625541941393]}},{"type":"Feature","properties":{"nom":"Auriac","code":"19014","codeDepartement":"19","codeRegion":"75","codesPostaux":["19220"],"population":231},"geometry":{"type":"Point","coordinates":[2.140546092741931,45.19965503091395]}},{"type":"Feature","properties":{"nom":"Ayen","code":"19015","codeDepartement":"19","codeRegion":"75","codesPostaux":["19310"],"population":721},"geometry":{"type":"Point","coordinates":[1.324525307692307,45.256751060897436]}},{"type":"Feature","properties":{"nom":"Bar","code":"19016","codeDepartement":"19","codeRegion":"75","codesPostaux":["19800"],"population":311},"geometry":{"type":"Point","coordinates":[1.8133740555058198,45.34548779767235]}},{"type":"Feature","properties":{"nom":"Bassignac-le-Bas","code":"19017","codeDepartement":"19","codeRegion":"75","codesPostaux":["19430"],"population":92},"geometry":{"type":"Point","coordinates":[1.8713301070745718,45.02715450669216]}},{"type":"Feature","properties":{"nom":"Bassignac-le-Haut","code":"19018","codeDepartement":"19","codeRegion":"75","codesPostaux":["19220"],"population":189},"geometry":{"type":"Point","coordinates":[2.0696395945454533,45.19680320545456]}},{"type":"Feature","properties":{"nom":"Beaulieu-sur-Dordogne","code":"19019","codeDepartement":"19","codeRegion":"75","codesPostaux":["19120"],"population":1320},"geometry":{"type":"Point","coordinates":[1.831559108142493,45.00340668956742]}},{"type":"Feature","properties":{"nom":"Beaumont","code":"19020","codeDepartement":"19","codeRegion":"75","codesPostaux":["19390"],"population":116},"geometry":{"type":"Point","coordinates":[1.790863022491348,45.42314301730101]}},{"type":"Feature","properties":{"nom":"Bellechassagne","code":"19021","codeDepartement":"19","codeRegion":"75","codesPostaux":["19290"],"population":87},"geometry":{"type":"Point","coordinates":[2.2120256987951805,45.64683258232932]}},{"type":"Feature","properties":{"nom":"Benayes","code":"19022","codeDepartement":"19","codeRegion":"75","codesPostaux":["19510"],"population":231},"geometry":{"type":"Point","coordinates":[1.4689579821240797,45.51905765615137]}},{"type":"Feature","properties":{"nom":"Beynat","code":"19023","codeDepartement":"19","codeRegion":"75","codesPostaux":["19190"],"population":1272},"geometry":{"type":"Point","coordinates":[1.7231639737532798,45.12677475328085]}},{"type":"Feature","properties":{"nom":"Beyssac","code":"19024","codeDepartement":"19","codeRegion":"75","codesPostaux":["19230"],"population":623},"geometry":{"type":"Point","coordinates":[1.4264580808219176,45.36478722054797]}},{"type":"Feature","properties":{"nom":"Beyssenac","code":"19025","codeDepartement":"19","codeRegion":"75","codesPostaux":["19230"],"population":372},"geometry":{"type":"Point","coordinates":[1.2991505362853624,45.4009470479705]}},{"type":"Feature","properties":{"nom":"Bilhac","code":"19026","codeDepartement":"19","codeRegion":"75","codesPostaux":["19120"],"population":229},"geometry":{"type":"Point","coordinates":[1.7780187192982473,44.94535572514621]}},{"type":"Feature","properties":{"nom":"Bonnefond","code":"19027","codeDepartement":"19","codeRegion":"75","codesPostaux":["19170"],"population":112},"geometry":{"type":"Point","coordinates":[1.982872695742472,45.524428974039544]}},{"type":"Feature","properties":{"nom":"Bort-les-Orgues","code":"19028","codeDepartement":"19","codeRegion":"75","codesPostaux":["19110"],"population":2699},"geometry":{"type":"Point","coordinates":[2.4896763625218923,45.39182079684765]}},{"type":"Feature","properties":{"nom":"Branceilles","code":"19029","codeDepartement":"19","codeRegion":"75","codesPostaux":["19500"],"population":277},"geometry":{"type":"Point","coordinates":[1.7130108608695642,45.00696998840581]}},{"type":"Feature","properties":{"nom":"Brignac-la-Plaine","code":"19030","codeDepartement":"19","codeRegion":"75","codesPostaux":["19310"],"population":987},"geometry":{"type":"Point","coordinates":[1.3329555128552104,45.177704761840324]}},{"type":"Feature","properties":{"nom":"Brive-la-Gaillarde","code":"19031","codeDepartement":"19","codeRegion":"75","codesPostaux":["19100"],"population":47004},"geometry":{"type":"Point","coordinates":[1.5155249204545451,45.139280081611524]}},{"type":"Feature","properties":{"nom":"Bugeat","code":"19033","codeDepartement":"19","codeRegion":"75","codesPostaux":["19170"],"population":816},"geometry":{"type":"Point","coordinates":[1.942992417061612,45.59448788309634]}},{"type":"Feature","properties":{"nom":"Camps-Saint-Mathurin-Léobazel","code":"19034","codeDepartement":"19","codeRegion":"75","codesPostaux":["19430"],"population":240},"geometry":{"type":"Point","coordinates":[1.9876116016260146,44.99379146225318]}},{"type":"Feature","properties":{"nom":"Chabrignac","code":"19035","codeDepartement":"19","codeRegion":"75","codesPostaux":["19350"],"population":585},"geometry":{"type":"Point","coordinates":[1.3401520465116277,45.31208186469339]}},{"type":"Feature","properties":{"nom":"Chamberet","code":"19036","codeDepartement":"19","codeRegion":"75","codesPostaux":["19370"],"population":1367},"geometry":{"type":"Point","coordinates":[1.721297271671133,45.610391668453964]}},{"type":"Feature","properties":{"nom":"Chamboulive","code":"19037","codeDepartement":"19","codeRegion":"75","codesPostaux":["19450"],"population":1204},"geometry":{"type":"Point","coordinates":[1.7111684696356269,45.42692592307693]}},{"type":"Feature","properties":{"nom":"Chameyrat","code":"19038","codeDepartement":"19","codeRegion":"75","codesPostaux":["19330"],"population":1552},"geometry":{"type":"Point","coordinates":[1.7098526155038742,45.248610396899274]}},{"type":"Feature","properties":{"nom":"Champagnac-la-Noaille","code":"19039","codeDepartement":"19","codeRegion":"75","codesPostaux":["19320"],"population":239},"geometry":{"type":"Point","coordinates":[1.9930406108786614,45.30604617991632]}},{"type":"Feature","properties":{"nom":"Champagnac-la-Prune","code":"19040","codeDepartement":"19","codeRegion":"75","codesPostaux":["19320"],"population":163},"geometry":{"type":"Point","coordinates":[1.9398755905349792,45.18626858230453]}},{"type":"Feature","properties":{"nom":"Chanac-les-Mines","code":"19041","codeDepartement":"19","codeRegion":"75","codesPostaux":["19150"],"population":509},"geometry":{"type":"Point","coordinates":[1.815933195402298,45.26853844663378]}},{"type":"Feature","properties":{"nom":"Chanteix","code":"19042","codeDepartement":"19","codeRegion":"75","codesPostaux":["19330"],"population":601},"geometry":{"type":"Point","coordinates":[1.6257362826362467,45.310704778200204]}},{"type":"Feature","properties":{"nom":"La Chapelle-aux-Brocs","code":"19043","codeDepartement":"19","codeRegion":"75","codesPostaux":["19360"],"population":420},"geometry":{"type":"Point","coordinates":[1.6251321486486483,45.14500039414415]}},{"type":"Feature","properties":{"nom":"La Chapelle-aux-Saints","code":"19044","codeDepartement":"19","codeRegion":"75","codesPostaux":["19120"],"population":259},"geometry":{"type":"Point","coordinates":[1.7211460445205486,44.98413584931506]}},{"type":"Feature","properties":{"nom":"La Chapelle-Saint-Géraud","code":"19045","codeDepartement":"19","codeRegion":"75","codesPostaux":["19430"],"population":201},"geometry":{"type":"Point","coordinates":[1.9490907826086938,45.048710886956535]}},{"type":"Feature","properties":{"nom":"Chapelle-Spinasse","code":"19046","codeDepartement":"19","codeRegion":"75","codesPostaux":["19300"],"population":116},"geometry":{"type":"Point","coordinates":[2.0494581366279094,45.35703483139535]}},{"type":"Feature","properties":{"nom":"Chartrier-Ferrière","code":"19047","codeDepartement":"19","codeRegion":"75","codesPostaux":["19600"],"population":367},"geometry":{"type":"Point","coordinates":[1.4324739251870324,45.05936693017459]}},{"type":"Feature","properties":{"nom":"Le Chastang","code":"19048","codeDepartement":"19","codeRegion":"75","codesPostaux":["19190"],"population":371},"geometry":{"type":"Point","coordinates":[1.732523586538462,45.18002522115384]}},{"type":"Feature","properties":{"nom":"Chasteaux","code":"19049","codeDepartement":"19","codeRegion":"75","codesPostaux":["19600"],"population":771},"geometry":{"type":"Point","coordinates":[1.4680366063829786,45.08708338829782]}},{"type":"Feature","properties":{"nom":"Chauffour-sur-Vell","code":"19050","codeDepartement":"19","codeRegion":"75","codesPostaux":["19500"],"population":422},"geometry":{"type":"Point","coordinates":[1.6722978965517246,45.020352031348004]}},{"type":"Feature","properties":{"nom":"Chaumeil","code":"19051","codeDepartement":"19","codeRegion":"75","codesPostaux":["19390"],"population":155},"geometry":{"type":"Point","coordinates":[1.8826526163265305,45.451305875510236]}},{"type":"Feature","properties":{"nom":"Chavanac","code":"19052","codeDepartement":"19","codeRegion":"75","codesPostaux":["19290"],"population":52},"geometry":{"type":"Point","coordinates":[2.091604146892654,45.61762678813561]}},{"type":"Feature","properties":{"nom":"Chaveroche","code":"19053","codeDepartement":"19","codeRegion":"75","codesPostaux":["19200"],"population":218},"geometry":{"type":"Point","coordinates":[2.2515298601036258,45.560651911917134]}},{"type":"Feature","properties":{"nom":"Chenailler-Mascheix","code":"19054","codeDepartement":"19","codeRegion":"75","codesPostaux":["19120"],"population":205},"geometry":{"type":"Point","coordinates":[1.823932258751901,45.062364607305895]}},{"type":"Feature","properties":{"nom":"Chirac-Bellevue","code":"19055","codeDepartement":"19","codeRegion":"75","codesPostaux":["19160"],"population":291},"geometry":{"type":"Point","coordinates":[2.3143542190082607,45.45059477892568]}},{"type":"Feature","properties":{"nom":"Clergoux","code":"19056","codeDepartement":"19","codeRegion":"75","codesPostaux":["19320"],"population":415},"geometry":{"type":"Point","coordinates":[1.9580229976798138,45.280855269141526]}},{"type":"Feature","properties":{"nom":"Collonges-la-Rouge","code":"19057","codeDepartement":"19","codeRegion":"75","codesPostaux":["19500"],"population":488},"geometry":{"type":"Point","coordinates":[1.6529501517367455,45.067134519195626]}},{"type":"Feature","properties":{"nom":"Combressol","code":"19058","codeDepartement":"19","codeRegion":"75","codesPostaux":["19250"],"population":348},"geometry":{"type":"Point","coordinates":[2.1546459503311266,45.47389552649006]}},{"type":"Feature","properties":{"nom":"Concèze","code":"19059","codeDepartement":"19","codeRegion":"75","codesPostaux":["19350"],"population":424},"geometry":{"type":"Point","coordinates":[1.3418713400335,45.35789407537689]}},{"type":"Feature","properties":{"nom":"Condat-sur-Ganaveix","code":"19060","codeDepartement":"19","codeRegion":"75","codesPostaux":["19140"],"population":664},"geometry":{"type":"Point","coordinates":[1.5899692647601467,45.477858053505415]}},{"type":"Feature","properties":{"nom":"Cornil","code":"19061","codeDepartement":"19","codeRegion":"75","codesPostaux":["19150"],"population":1369},"geometry":{"type":"Point","coordinates":[1.700771539052497,45.213658865557]}},{"type":"Feature","properties":{"nom":"Corrèze","code":"19062","codeDepartement":"19","codeRegion":"75","codesPostaux":["19800"],"population":1126},"geometry":{"type":"Point","coordinates":[1.8644051064400722,45.36922763953493]}},{"type":"Feature","properties":{"nom":"Cosnac","code":"19063","codeDepartement":"19","codeRegion":"75","codesPostaux":["19360"],"population":2984},"geometry":{"type":"Point","coordinates":[1.5908624461325962,45.13533473618788]}},{"type":"Feature","properties":{"nom":"Couffy-sur-Sarsonne","code":"19064","codeDepartement":"19","codeRegion":"75","codesPostaux":["19340"],"population":78},"geometry":{"type":"Point","coordinates":[2.340858836787565,45.67060236528497]}},{"type":"Feature","properties":{"nom":"Courteix","code":"19065","codeDepartement":"19","codeRegion":"75","codesPostaux":["19340"],"population":64},"geometry":{"type":"Point","coordinates":[2.342990353535354,45.651927707070705]}},{"type":"Feature","properties":{"nom":"Cublac","code":"19066","codeDepartement":"19","codeRegion":"75","codesPostaux":["19520"],"population":1674},"geometry":{"type":"Point","coordinates":[1.312782458270106,45.15618916540212]}},{"type":"Feature","properties":{"nom":"Curemonte","code":"19067","codeDepartement":"19","codeRegion":"75","codesPostaux":["19500"],"population":211},"geometry":{"type":"Point","coordinates":[1.7546846007984036,45.004113019960094]}},{"type":"Feature","properties":{"nom":"Dampniat","code":"19068","codeDepartement":"19","codeRegion":"75","codesPostaux":["19360"],"population":743},"geometry":{"type":"Point","coordinates":[1.6369546688481673,45.160695712041864]}},{"type":"Feature","properties":{"nom":"Darazac","code":"19069","codeDepartement":"19","codeRegion":"75","codesPostaux":["19220"],"population":136},"geometry":{"type":"Point","coordinates":[2.081651086826347,45.17188249850298]}},{"type":"Feature","properties":{"nom":"Darnets","code":"19070","codeDepartement":"19","codeRegion":"75","codesPostaux":["19300"],"population":360},"geometry":{"type":"Point","coordinates":[2.1185993275590524,45.41821294488192]}},{"type":"Feature","properties":{"nom":"Davignac","code":"19071","codeDepartement":"19","codeRegion":"75","codesPostaux":["19250"],"population":213},"geometry":{"type":"Point","coordinates":[2.077508375000002,45.49243722033896]}},{"type":"Feature","properties":{"nom":"Donzenac","code":"19072","codeDepartement":"19","codeRegion":"75","codesPostaux":["19270"],"population":2646},"geometry":{"type":"Point","coordinates":[1.5278330803324083,45.23092645844875]}},{"type":"Feature","properties":{"nom":"Égletons","code":"19073","codeDepartement":"19","codeRegion":"75","codesPostaux":["19300"],"population":4287},"geometry":{"type":"Point","coordinates":[2.034226059907834,45.422600701996934]}},{"type":"Feature","properties":{"nom":"L'Église-aux-Bois","code":"19074","codeDepartement":"19","codeRegion":"75","codesPostaux":["19170"],"population":56},"geometry":{"type":"Point","coordinates":[1.7932922151029747,45.654979054919934]}},{"type":"Feature","properties":{"nom":"Espagnac","code":"19075","codeDepartement":"19","codeRegion":"75","codesPostaux":["19150"],"population":373},"geometry":{"type":"Point","coordinates":[1.8870973789097405,45.24173889454867]}},{"type":"Feature","properties":{"nom":"Espartignac","code":"19076","codeDepartement":"19","codeRegion":"75","codesPostaux":["19140"],"population":440},"geometry":{"type":"Point","coordinates":[1.5996396037735854,45.40006569182399]}},{"type":"Feature","properties":{"nom":"Estivals","code":"19077","codeDepartement":"19","codeRegion":"75","codesPostaux":["19600"],"population":126},"geometry":{"type":"Point","coordinates":[1.4594474375000008,45.03147265384613]}},{"type":"Feature","properties":{"nom":"Estivaux","code":"19078","codeDepartement":"19","codeRegion":"75","codesPostaux":["19410"],"population":425},"geometry":{"type":"Point","coordinates":[1.4964560924855492,45.32126167052021]}},{"type":"Feature","properties":{"nom":"Eyburie","code":"19079","codeDepartement":"19","codeRegion":"75","codesPostaux":["19140"],"population":494},"geometry":{"type":"Point","coordinates":[1.6370740268361599,45.46700110875703]}},{"type":"Feature","properties":{"nom":"Eygurande","code":"19080","codeDepartement":"19","codeRegion":"75","codesPostaux":["19340"],"population":683},"geometry":{"type":"Point","coordinates":[2.422523134057971,45.683139514492765]}},{"type":"Feature","properties":{"nom":"Eyrein","code":"19081","codeDepartement":"19","codeRegion":"75","codesPostaux":["19800"],"population":497},"geometry":{"type":"Point","coordinates":[1.9560995717647047,45.32822042823531]}},{"type":"Feature","properties":{"nom":"Favars","code":"19082","codeDepartement":"19","codeRegion":"75","codesPostaux":["19330"],"population":1058},"geometry":{"type":"Point","coordinates":[1.6691121076923081,45.265193838461535]}},{"type":"Feature","properties":{"nom":"Feyt","code":"19083","codeDepartement":"19","codeRegion":"75","codesPostaux":["19340"],"population":129},"geometry":{"type":"Point","coordinates":[2.4867324229508188,45.683181290163894]}},{"type":"Feature","properties":{"nom":"Forgès","code":"19084","codeDepartement":"19","codeRegion":"75","codesPostaux":["19380"],"population":303},"geometry":{"type":"Point","coordinates":[1.8643507859922175,45.16121433852133]}},{"type":"Feature","properties":{"nom":"Gimel-les-Cascades","code":"19085","codeDepartement":"19","codeRegion":"75","codesPostaux":["19800"],"population":787},"geometry":{"type":"Point","coordinates":[1.839545445086706,45.300154218497084]}},{"type":"Feature","properties":{"nom":"Goulles","code":"19086","codeDepartement":"19","codeRegion":"75","codesPostaux":["19430"],"population":327},"geometry":{"type":"Point","coordinates":[2.0840809127459314,45.01995413772462]}},{"type":"Feature","properties":{"nom":"Gourdon-Murat","code":"19087","codeDepartement":"19","codeRegion":"75","codesPostaux":["19170"],"population":109},"geometry":{"type":"Point","coordinates":[1.8981087161290324,45.5426600387097]}},{"type":"Feature","properties":{"nom":"Grandsaigne","code":"19088","codeDepartement":"19","codeRegion":"75","codesPostaux":["19300"],"population":50},"geometry":{"type":"Point","coordinates":[1.9333115031347952,45.487593100313454]}},{"type":"Feature","properties":{"nom":"Gros-Chastang","code":"19089","codeDepartement":"19","codeRegion":"75","codesPostaux":["19320"],"population":179},"geometry":{"type":"Point","coordinates":[2.0048543645038155,45.21380891030536]}},{"type":"Feature","properties":{"nom":"Gumond","code":"19090","codeDepartement":"19","codeRegion":"75","codesPostaux":["19320"],"population":96},"geometry":{"type":"Point","coordinates":[1.9651851566579617,45.22269581201042]}},{"type":"Feature","properties":{"nom":"Hautefage","code":"19091","codeDepartement":"19","codeRegion":"75","codesPostaux":["19400"],"population":310},"geometry":{"type":"Point","coordinates":[1.9864776625000016,45.094673459999996]}},{"type":"Feature","properties":{"nom":"Le Jardin","code":"19092","codeDepartement":"19","codeRegion":"75","codesPostaux":["19300"],"population":83},"geometry":{"type":"Point","coordinates":[2.038247418502203,45.32298896916301]}},{"type":"Feature","properties":{"nom":"Jugeals-Nazareth","code":"19093","codeDepartement":"19","codeRegion":"75","codesPostaux":["19500"],"population":956},"geometry":{"type":"Point","coordinates":[1.5561848746987952,45.089603780722896]}},{"type":"Feature","properties":{"nom":"Juillac","code":"19094","codeDepartement":"19","codeRegion":"75","codesPostaux":["19350"],"population":1127},"geometry":{"type":"Point","coordinates":[1.2937932783933508,45.31769138642658]}},{"type":"Feature","properties":{"nom":"Lacelle","code":"19095","codeDepartement":"19","codeRegion":"75","codesPostaux":["19170"],"population":134},"geometry":{"type":"Point","coordinates":[1.8260458932926817,45.64271941463412]}},{"type":"Feature","properties":{"nom":"Ladignac-sur-Rondelles","code":"19096","codeDepartement":"19","codeRegion":"75","codesPostaux":["19150"],"population":412},"geometry":{"type":"Point","coordinates":[1.8260956748582233,45.23203859357275]}},{"type":"Feature","properties":{"nom":"Lafage-sur-Sombre","code":"19097","codeDepartement":"19","codeRegion":"75","codesPostaux":["19320"],"population":120},"geometry":{"type":"Point","coordinates":[2.0697625746388444,45.291455418940544]}},{"type":"Feature","properties":{"nom":"Lagarde-Marc-la-Tour","code":"19098","codeDepartement":"19","codeRegion":"75","codesPostaux":["19150"],"population":979},"geometry":{"type":"Point","coordinates":[1.826608413294796,45.187609031791915]}},{"type":"Feature","properties":{"nom":"Lagleygeolle","code":"19099","codeDepartement":"19","codeRegion":"75","codesPostaux":["19500"],"population":219},"geometry":{"type":"Point","coordinates":[1.6922402037533497,45.086395796246606]}},{"type":"Feature","properties":{"nom":"Lagraulière","code":"19100","codeDepartement":"19","codeRegion":"75","codesPostaux":["19700"],"population":1104},"geometry":{"type":"Point","coordinates":[1.6264884915797917,45.35494227024853]}},{"type":"Feature","properties":{"nom":"Laguenne-sur-Avalouze","code":"19101","codeDepartement":"19","codeRegion":"75","codesPostaux":["19150"],"population":1550},"geometry":{"type":"Point","coordinates":[1.8106582403486917,45.24910808841845]}},{"type":"Feature","properties":{"nom":"Lamazière-Basse","code":"19102","codeDepartement":"19","codeRegion":"75","codesPostaux":["19160"],"population":300},"geometry":{"type":"Point","coordinates":[2.1704972986906714,45.36872710638295]}},{"type":"Feature","properties":{"nom":"Lamazière-Haute","code":"19103","codeDepartement":"19","codeRegion":"75","codesPostaux":["19340"],"population":66},"geometry":{"type":"Point","coordinates":[2.387257512110726,45.673235103806235]}},{"type":"Feature","properties":{"nom":"Lamongerie","code":"19104","codeDepartement":"19","codeRegion":"75","codesPostaux":["19510"],"population":115},"geometry":{"type":"Point","coordinates":[1.5769282529711393,45.54022579117146]}},{"type":"Feature","properties":{"nom":"Lanteuil","code":"19105","codeDepartement":"19","codeRegion":"75","codesPostaux":["19190"],"population":522},"geometry":{"type":"Point","coordinates":[1.642586316644113,45.11835014884977]}},{"type":"Feature","properties":{"nom":"Lapleau","code":"19106","codeDepartement":"19","codeRegion":"75","codesPostaux":["19550"],"population":388},"geometry":{"type":"Point","coordinates":[2.158614720101781,45.29421280407129]}},{"type":"Feature","properties":{"nom":"Larche","code":"19107","codeDepartement":"19","codeRegion":"75","codesPostaux":["19600"],"population":1595},"geometry":{"type":"Point","coordinates":[1.4147915008818341,45.11220875485007]}},{"type":"Feature","properties":{"nom":"Laroche-près-Feyt","code":"19108","codeDepartement":"19","codeRegion":"75","codesPostaux":["19340"],"population":64},"geometry":{"type":"Point","coordinates":[2.5004372683706118,45.70659697284345]}},{"type":"Feature","properties":{"nom":"Lascaux","code":"19109","codeDepartement":"19","codeRegion":"75","codesPostaux":["19130"],"population":212},"geometry":{"type":"Point","coordinates":[1.3711703051948039,45.34115701515153]}},{"type":"Feature","properties":{"nom":"Latronche","code":"19110","codeDepartement":"19","codeRegion":"75","codesPostaux":["19160"],"population":135},"geometry":{"type":"Point","coordinates":[2.239713081818183,45.31032137727269]}},{"type":"Feature","properties":{"nom":"Laval-sur-Luzège","code":"19111","codeDepartement":"19","codeRegion":"75","codesPostaux":["19550"],"population":99},"geometry":{"type":"Point","coordinates":[2.136797481072555,45.25763509936908]}},{"type":"Feature","properties":{"nom":"Lestards","code":"19112","codeDepartement":"19","codeRegion":"75","codesPostaux":["19170"],"population":105},"geometry":{"type":"Point","coordinates":[1.8629904609120524,45.54216573289905]}},{"type":"Feature","properties":{"nom":"Liginiac","code":"19113","codeDepartement":"19","codeRegion":"75","codesPostaux":["19160"],"population":583},"geometry":{"type":"Point","coordinates":[2.323877386138615,45.41293608250826]}},{"type":"Feature","properties":{"nom":"Lignareix","code":"19114","codeDepartement":"19","codeRegion":"75","codesPostaux":["19200"],"population":164},"geometry":{"type":"Point","coordinates":[2.3045191786666654,45.60290344266668]}},{"type":"Feature","properties":{"nom":"Ligneyrac","code":"19115","codeDepartement":"19","codeRegion":"75","codesPostaux":["19500"],"population":307},"geometry":{"type":"Point","coordinates":[1.6183336411889617,45.04794999363058]}},{"type":"Feature","properties":{"nom":"Liourdres","code":"19116","codeDepartement":"19","codeRegion":"75","codesPostaux":["19120"],"population":250},"geometry":{"type":"Point","coordinates":[1.8056907604790426,44.93871673652691]}},{"type":"Feature","properties":{"nom":"Lissac-sur-Couze","code":"19117","codeDepartement":"19","codeRegion":"75","codesPostaux":["19600"],"population":749},"geometry":{"type":"Point","coordinates":[1.460206511627907,45.1099562938689]}},{"type":"Feature","properties":{"nom":"Le Lonzac","code":"19118","codeDepartement":"19","codeRegion":"75","codesPostaux":["19470"],"population":802},"geometry":{"type":"Point","coordinates":[1.735180127049179,45.46850879918029]}},{"type":"Feature","properties":{"nom":"Lostanges","code":"19119","codeDepartement":"19","codeRegion":"75","codesPostaux":["19500"],"population":134},"geometry":{"type":"Point","coordinates":[1.773612626242544,45.0686212723658]}},{"type":"Feature","properties":{"nom":"Louignac","code":"19120","codeDepartement":"19","codeRegion":"75","codesPostaux":["19310"],"population":237},"geometry":{"type":"Point","coordinates":[1.2802543746223571,45.218989806646526]}},{"type":"Feature","properties":{"nom":"Lubersac","code":"19121","codeDepartement":"19","codeRegion":"75","codesPostaux":["19210"],"population":2225},"geometry":{"type":"Point","coordinates":[1.4014550200471683,45.45521283018861]}},{"type":"Feature","properties":{"nom":"Madranges","code":"19122","codeDepartement":"19","codeRegion":"75","codesPostaux":["19470"],"population":193},"geometry":{"type":"Point","coordinates":[1.796426561403508,45.46859797465884]}},{"type":"Feature","properties":{"nom":"Malemort","code":"19123","codeDepartement":"19","codeRegion":"75","codesPostaux":["19360"],"population":8012},"geometry":{"type":"Point","coordinates":[1.5930541147132176,45.18166756982552]}},{"type":"Feature","properties":{"nom":"Mansac","code":"19124","codeDepartement":"19","codeRegion":"75","codesPostaux":["19520"],"population":1420},"geometry":{"type":"Point","coordinates":[1.3797868438320198,45.161942108923824]}},{"type":"Feature","properties":{"nom":"Marcillac-la-Croisille","code":"19125","codeDepartement":"19","codeRegion":"75","codesPostaux":["19320"],"population":796},"geometry":{"type":"Point","coordinates":[2.0283800890642607,45.254090908680894]}},{"type":"Feature","properties":{"nom":"Marcillac-la-Croze","code":"19126","codeDepartement":"19","codeRegion":"75","codesPostaux":["19500"],"population":179},"geometry":{"type":"Point","coordinates":[1.7384842169491526,45.03378604067798]}},{"type":"Feature","properties":{"nom":"Margerides","code":"19128","codeDepartement":"19","codeRegion":"75","codesPostaux":["19200"],"population":299},"geometry":{"type":"Point","coordinates":[2.4131604417744903,45.45400755822552]}},{"type":"Feature","properties":{"nom":"Masseret","code":"19129","codeDepartement":"19","codeRegion":"75","codesPostaux":["19510"],"population":682},"geometry":{"type":"Point","coordinates":[1.5220135413533824,45.54249260902252]}},{"type":"Feature","properties":{"nom":"Maussac","code":"19130","codeDepartement":"19","codeRegion":"75","codesPostaux":["19250"],"population":435},"geometry":{"type":"Point","coordinates":[2.1261970627802693,45.472334363228676]}},{"type":"Feature","properties":{"nom":"Meilhards","code":"19131","codeDepartement":"19","codeRegion":"75","codesPostaux":["19510"],"population":507},"geometry":{"type":"Point","coordinates":[1.6331052015503875,45.545924922480644]}},{"type":"Feature","properties":{"nom":"Ménoire","code":"19132","codeDepartement":"19","codeRegion":"75","codesPostaux":["19190"],"population":112},"geometry":{"type":"Point","coordinates":[1.7946146790830955,45.10593132951287]}},{"type":"Feature","properties":{"nom":"Mercœur","code":"19133","codeDepartement":"19","codeRegion":"75","codesPostaux":["19430"],"population":248},"geometry":{"type":"Point","coordinates":[1.9484069481641455,45.013247987041034]}},{"type":"Feature","properties":{"nom":"Merlines","code":"19134","codeDepartement":"19","codeRegion":"75","codesPostaux":["19340"],"population":731},"geometry":{"type":"Point","coordinates":[2.463028709239129,45.626673086956515]}},{"type":"Feature","properties":{"nom":"Mestes","code":"19135","codeDepartement":"19","codeRegion":"75","codesPostaux":["19200"],"population":356},"geometry":{"type":"Point","coordinates":[2.3160259025000007,45.494466187500024]}},{"type":"Feature","properties":{"nom":"Meymac","code":"19136","codeDepartement":"19","codeRegion":"75","codesPostaux":["19250"],"population":2411},"geometry":{"type":"Point","coordinates":[2.1406195727848116,45.54962167278485]}},{"type":"Feature","properties":{"nom":"Meyrignac-l'Église","code":"19137","codeDepartement":"19","codeRegion":"75","codesPostaux":["19800"],"population":62},"geometry":{"type":"Point","coordinates":[1.862366510318947,45.401899666041274]}},{"type":"Feature","properties":{"nom":"Meyssac","code":"19138","codeDepartement":"19","codeRegion":"75","codesPostaux":["19500"],"population":1283},"geometry":{"type":"Point","coordinates":[1.6854629317180607,45.05105406167402]}},{"type":"Feature","properties":{"nom":"Millevaches","code":"19139","codeDepartement":"19","codeRegion":"75","codesPostaux":["19290"],"population":83},"geometry":{"type":"Point","coordinates":[2.0869049130434787,45.63977482608699]}},{"type":"Feature","properties":{"nom":"Monceaux-sur-Dordogne","code":"19140","codeDepartement":"19","codeRegion":"75","codesPostaux":["19400"],"population":639},"geometry":{"type":"Point","coordinates":[1.8821181150442468,45.07271654719764]}},{"type":"Feature","properties":{"nom":"Monestier-Merlines","code":"19141","codeDepartement":"19","codeRegion":"75","codesPostaux":["19340"],"population":313},"geometry":{"type":"Point","coordinates":[2.489377896464648,45.64810322474744]}},{"type":"Feature","properties":{"nom":"Monestier-Port-Dieu","code":"19142","codeDepartement":"19","codeRegion":"75","codesPostaux":["19110"],"population":106},"geometry":{"type":"Point","coordinates":[2.4888556502463057,45.505340532019744]}},{"type":"Feature","properties":{"nom":"Montaignac-Saint-Hippolyte","code":"19143","codeDepartement":"19","codeRegion":"75","codesPostaux":["19300"],"population":576},"geometry":{"type":"Point","coordinates":[2.0181289923857855,45.34606525253801]}},{"type":"Feature","properties":{"nom":"Montgibaud","code":"19144","codeDepartement":"19","codeRegion":"75","codesPostaux":["19210"],"population":241},"geometry":{"type":"Point","coordinates":[1.4206531617647071,45.50980029411762]}},{"type":"Feature","properties":{"nom":"Moustier-Ventadour","code":"19145","codeDepartement":"19","codeRegion":"75","codesPostaux":["19300"],"population":472},"geometry":{"type":"Point","coordinates":[2.1064515923836415,45.379993798307474]}},{"type":"Feature","properties":{"nom":"Naves","code":"19146","codeDepartement":"19","codeRegion":"75","codesPostaux":["19460"],"population":2325},"geometry":{"type":"Point","coordinates":[1.7446097503526081,45.31323390620595]}},{"type":"Feature","properties":{"nom":"Nespouls","code":"19147","codeDepartement":"19","codeRegion":"75","codesPostaux":["19600"],"population":632},"geometry":{"type":"Point","coordinates":[1.5019827135549868,45.05452174936059]}},{"type":"Feature","properties":{"nom":"Neuvic","code":"19148","codeDepartement":"19","codeRegion":"75","codesPostaux":["19160"],"population":1668},"geometry":{"type":"Point","coordinates":[2.257242178378378,45.358978902702674]}},{"type":"Feature","properties":{"nom":"Neuville","code":"19149","codeDepartement":"19","codeRegion":"75","codesPostaux":["19380"],"population":190},"geometry":{"type":"Point","coordinates":[1.847213021067417,45.10995299157302]}},{"type":"Feature","properties":{"nom":"Noailhac","code":"19150","codeDepartement":"19","codeRegion":"75","codesPostaux":["19500"],"population":379},"geometry":{"type":"Point","coordinates":[1.62032010948905,45.08421324635042]}},{"type":"Feature","properties":{"nom":"Noailles","code":"19151","codeDepartement":"19","codeRegion":"75","codesPostaux":["19600"],"population":895},"geometry":{"type":"Point","coordinates":[1.5180369807692313,45.099092454326914]}},{"type":"Feature","properties":{"nom":"Nonards","code":"19152","codeDepartement":"19","codeRegion":"75","codesPostaux":["19120"],"population":454},"geometry":{"type":"Point","coordinates":[1.8095303910256404,45.01738347275643]}},{"type":"Feature","properties":{"nom":"Objat","code":"19153","codeDepartement":"19","codeRegion":"75","codesPostaux":["19130"],"population":3652},"geometry":{"type":"Point","coordinates":[1.4113608470588244,45.26687294901961]}},{"type":"Feature","properties":{"nom":"Orgnac-sur-Vézère","code":"19154","codeDepartement":"19","codeRegion":"75","codesPostaux":["19410"],"population":312},"geometry":{"type":"Point","coordinates":[1.4536287638888885,45.34079347067903]}},{"type":"Feature","properties":{"nom":"Orliac-de-Bar","code":"19155","codeDepartement":"19","codeRegion":"75","codesPostaux":["19390"],"population":292},"geometry":{"type":"Point","coordinates":[1.8046296885906035,45.37052023221478]}},{"type":"Feature","properties":{"nom":"Palazinges","code":"19156","codeDepartement":"19","codeRegion":"75","codesPostaux":["19190"],"population":148},"geometry":{"type":"Point","coordinates":[1.6889847200000003,45.16515047]}},{"type":"Feature","properties":{"nom":"Palisse","code":"19157","codeDepartement":"19","codeRegion":"75","codesPostaux":["19160"],"population":227},"geometry":{"type":"Point","coordinates":[2.1975040929203535,45.42610268584069]}},{"type":"Feature","properties":{"nom":"Pandrignes","code":"19158","codeDepartement":"19","codeRegion":"75","codesPostaux":["19150"],"population":164},"geometry":{"type":"Point","coordinates":[1.8599502696850398,45.220653251968535]}},{"type":"Feature","properties":{"nom":"Péret-Bel-Air","code":"19159","codeDepartement":"19","codeRegion":"75","codesPostaux":["19300"],"population":92},"geometry":{"type":"Point","coordinates":[2.0259207765667573,45.475487264305166]}},{"type":"Feature","properties":{"nom":"Pérols-sur-Vézère","code":"19160","codeDepartement":"19","codeRegion":"75","codesPostaux":["19170"],"population":181},"geometry":{"type":"Point","coordinates":[1.9964069283639887,45.57621177444331]}},{"type":"Feature","properties":{"nom":"Perpezac-le-Blanc","code":"19161","codeDepartement":"19","codeRegion":"75","codesPostaux":["19310"],"population":469},"geometry":{"type":"Point","coordinates":[1.326236116972476,45.212800158256876]}},{"type":"Feature","properties":{"nom":"Perpezac-le-Noir","code":"19162","codeDepartement":"19","codeRegion":"75","codesPostaux":["19410"],"population":1133},"geometry":{"type":"Point","coordinates":[1.5541446513859236,45.33642545202566]}},{"type":"Feature","properties":{"nom":"Le Pescher","code":"19163","codeDepartement":"19","codeRegion":"75","codesPostaux":["19190"],"population":285},"geometry":{"type":"Point","coordinates":[1.7546817847866423,45.07888912987008]}},{"type":"Feature","properties":{"nom":"Peyrelevade","code":"19164","codeDepartement":"19","codeRegion":"75","codesPostaux":["19290"],"population":860},"geometry":{"type":"Point","coordinates":[2.032937561850804,45.710631629839426]}},{"type":"Feature","properties":{"nom":"Peyrissac","code":"19165","codeDepartement":"19","codeRegion":"75","codesPostaux":["19260"],"population":131},"geometry":{"type":"Point","coordinates":[1.6928173796610164,45.506706084745794]}},{"type":"Feature","properties":{"nom":"Pierrefitte","code":"19166","codeDepartement":"19","codeRegion":"75","codesPostaux":["19450"],"population":89},"geometry":{"type":"Point","coordinates":[1.647271252336449,45.42637369345794]}},{"type":"Feature","properties":{"nom":"Confolent-Port-Dieu","code":"19167","codeDepartement":"19","codeRegion":"75","codesPostaux":["19200"],"population":38},"geometry":{"type":"Point","coordinates":[2.494711080260304,45.530542537961004]}},{"type":"Feature","properties":{"nom":"Pradines","code":"19168","codeDepartement":"19","codeRegion":"75","codesPostaux":["19170"],"population":97},"geometry":{"type":"Point","coordinates":[1.9135022065813534,45.51416222486288]}},{"type":"Feature","properties":{"nom":"Puy-d'Arnac","code":"19169","codeDepartement":"19","codeRegion":"75","codesPostaux":["19120"],"population":289},"geometry":{"type":"Point","coordinates":[1.775070976190476,45.02479307509158]}},{"type":"Feature","properties":{"nom":"Queyssac-les-Vignes","code":"19170","codeDepartement":"19","codeRegion":"75","codesPostaux":["19120"],"population":198},"geometry":{"type":"Point","coordinates":[1.7709830448598138,44.96296204299064]}},{"type":"Feature","properties":{"nom":"Reygade","code":"19171","codeDepartement":"19","codeRegion":"75","codesPostaux":["19430"],"population":192},"geometry":{"type":"Point","coordinates":[1.903780333333335,45.02136265317921]}},{"type":"Feature","properties":{"nom":"Rilhac-Treignac","code":"19172","codeDepartement":"19","codeRegion":"75","codesPostaux":["19260"],"population":110},"geometry":{"type":"Point","coordinates":[1.6902873364197524,45.524692037037084]}},{"type":"Feature","properties":{"nom":"Rilhac-Xaintrie","code":"19173","codeDepartement":"19","codeRegion":"75","codesPostaux":["19220"],"population":304},"geometry":{"type":"Point","coordinates":[2.1891116151990344,45.171362862484884]}},{"type":"Feature","properties":{"nom":"La Roche-Canillac","code":"19174","codeDepartement":"19","codeRegion":"75","codesPostaux":["19320"],"population":146},"geometry":{"type":"Point","coordinates":[1.965499963114754,45.19751845901643]}},{"type":"Feature","properties":{"nom":"Roche-le-Peyroux","code":"19175","codeDepartement":"19","codeRegion":"75","codesPostaux":["19160"],"population":98},"geometry":{"type":"Point","coordinates":[2.3799184607142854,45.43013057500002]}},{"type":"Feature","properties":{"nom":"Rosiers-d'Égletons","code":"19176","codeDepartement":"19","codeRegion":"75","codesPostaux":["19300"],"population":1067},"geometry":{"type":"Point","coordinates":[2.008053728740583,45.390277615715746]}},{"type":"Feature","properties":{"nom":"Rosiers-de-Juillac","code":"19177","codeDepartement":"19","codeRegion":"75","codesPostaux":["19350"],"population":185},"geometry":{"type":"Point","coordinates":[1.3043937098445586,45.28800473747844]}},{"type":"Feature","properties":{"nom":"Sadroc","code":"19178","codeDepartement":"19","codeRegion":"75","codesPostaux":["19270"],"population":925},"geometry":{"type":"Point","coordinates":[1.5465137197875174,45.27323910092965]}},{"type":"Feature","properties":{"nom":"Saillac","code":"19179","codeDepartement":"19","codeRegion":"75","codesPostaux":["19500"],"population":208},"geometry":{"type":"Point","coordinates":[1.6399932746781114,45.04152836051502]}},{"type":"Feature","properties":{"nom":"Saint-Angel","code":"19180","codeDepartement":"19","codeRegion":"75","codesPostaux":["19200"],"population":707},"geometry":{"type":"Point","coordinates":[2.229534219395868,45.50398554372014]}},{"type":"Feature","properties":{"nom":"Saint-Augustin","code":"19181","codeDepartement":"19","codeRegion":"75","codesPostaux":["19390"],"population":424},"geometry":{"type":"Point","coordinates":[1.8271637384428252,45.43449972141125]}},{"type":"Feature","properties":{"nom":"Saint-Aulaire","code":"19182","codeDepartement":"19","codeRegion":"75","codesPostaux":["19130"],"population":799},"geometry":{"type":"Point","coordinates":[1.3916554838709683,45.23563392165897]}},{"type":"Feature","properties":{"nom":"Saint-Bazile-de-Meyssac","code":"19184","codeDepartement":"19","codeRegion":"75","codesPostaux":["19500"],"population":132},"geometry":{"type":"Point","coordinates":[1.7258363822393832,45.055406108108144]}},{"type":"Feature","properties":{"nom":"Saint-Bonnet-Elvert","code":"19186","codeDepartement":"19","codeRegion":"75","codesPostaux":["19380"],"population":208},"geometry":{"type":"Point","coordinates":[1.9190816072351418,45.15756266925062]}},{"type":"Feature","properties":{"nom":"Saint-Bonnet-la-Rivière","code":"19187","codeDepartement":"19","codeRegion":"75","codesPostaux":["19130"],"population":381},"geometry":{"type":"Point","coordinates":[1.3566267523148152,45.291594101851814]}},{"type":"Feature","properties":{"nom":"Saint-Bonnet-l'Enfantier","code":"19188","codeDepartement":"19","codeRegion":"75","codesPostaux":["19410"],"population":392},"geometry":{"type":"Point","coordinates":[1.533904427767355,45.29910019136956]}},{"type":"Feature","properties":{"nom":"Saint-Bonnet-les-Tours-de-Merle","code":"19189","codeDepartement":"19","codeRegion":"75","codesPostaux":["19430"],"population":50},"geometry":{"type":"Point","coordinates":[2.0515002063492056,45.051792583333295]}},{"type":"Feature","properties":{"nom":"Saint-Bonnet-près-Bort","code":"19190","codeDepartement":"19","codeRegion":"75","codesPostaux":["19200"],"population":194},"geometry":{"type":"Point","coordinates":[2.424495461538461,45.50482058974357]}},{"type":"Feature","properties":{"nom":"Saint-Cernin-de-Larche","code":"19191","codeDepartement":"19","codeRegion":"75","codesPostaux":["19600"],"population":655},"geometry":{"type":"Point","coordinates":[1.4151274115646257,45.09378284013606]}},{"type":"Feature","properties":{"nom":"Saint-Chamant","code":"19192","codeDepartement":"19","codeRegion":"75","codesPostaux":["19380"],"population":491},"geometry":{"type":"Point","coordinates":[1.8986597504488345,45.12714001795326]}},{"type":"Feature","properties":{"nom":"Saint-Cirgues-la-Loutre","code":"19193","codeDepartement":"19","codeRegion":"75","codesPostaux":["19220"],"population":177},"geometry":{"type":"Point","coordinates":[2.092279887719297,45.09231769473685]}},{"type":"Feature","properties":{"nom":"Saint-Clément","code":"19194","codeDepartement":"19","codeRegion":"75","codesPostaux":["19700"],"population":1322},"geometry":{"type":"Point","coordinates":[1.6822616780455146,45.32909523560916]}},{"type":"Feature","properties":{"nom":"Saint-Cyprien","code":"19195","codeDepartement":"19","codeRegion":"75","codesPostaux":["19130"],"population":387},"geometry":{"type":"Point","coordinates":[1.3547371876923076,45.25360556923072]}},{"type":"Feature","properties":{"nom":"Saint-Cyr-la-Roche","code":"19196","codeDepartement":"19","codeRegion":"75","codesPostaux":["19130"],"population":503},"geometry":{"type":"Point","coordinates":[1.3868405070821532,45.27712958640226]}},{"type":"Feature","properties":{"nom":"Saint-Éloy-les-Tuileries","code":"19198","codeDepartement":"19","codeRegion":"75","codesPostaux":["19210"],"population":104},"geometry":{"type":"Point","coordinates":[1.2761586628959267,45.454492076923074]}},{"type":"Feature","properties":{"nom":"Saint-Étienne-aux-Clos","code":"19199","codeDepartement":"19","codeRegion":"75","codesPostaux":["19200"],"population":227},"geometry":{"type":"Point","coordinates":[2.4568432585895126,45.566397804701616]}},{"type":"Feature","properties":{"nom":"Saint-Étienne-la-Geneste","code":"19200","codeDepartement":"19","codeRegion":"75","codesPostaux":["19160"],"population":94},"geometry":{"type":"Point","coordinates":[2.3449643745583,45.44871905300355]}},{"type":"Feature","properties":{"nom":"Saint-Exupéry-les-Roches","code":"19201","codeDepartement":"19","codeRegion":"75","codesPostaux":["19200"],"population":590},"geometry":{"type":"Point","coordinates":[2.368539550561799,45.50904304369535]}},{"type":"Feature","properties":{"nom":"Sainte-Féréole","code":"19202","codeDepartement":"19","codeRegion":"75","codesPostaux":["19270"],"population":1893},"geometry":{"type":"Point","coordinates":[1.5897687560521436,45.229932755121034]}},{"type":"Feature","properties":{"nom":"Sainte-Fortunade","code":"19203","codeDepartement":"19","codeRegion":"75","codesPostaux":["19490"],"population":1789},"geometry":{"type":"Point","coordinates":[1.7610839870129888,45.208801599763866]}},{"type":"Feature","properties":{"nom":"Saint-Fréjoux","code":"19204","codeDepartement":"19","codeRegion":"75","codesPostaux":["19200"],"population":293},"geometry":{"type":"Point","coordinates":[2.361978194260486,45.55235264900663]}},{"type":"Feature","properties":{"nom":"Saint-Geniez-ô-Merle","code":"19205","codeDepartement":"19","codeRegion":"75","codesPostaux":["19220"],"population":92},"geometry":{"type":"Point","coordinates":[2.068701083870968,45.08025069247309]}},{"type":"Feature","properties":{"nom":"Saint-Germain-Lavolps","code":"19206","codeDepartement":"19","codeRegion":"75","codesPostaux":["19290"],"population":87},"geometry":{"type":"Point","coordinates":[2.2014031841432224,45.60832827365731]}},{"type":"Feature","properties":{"nom":"Saint-Germain-les-Vergnes","code":"19207","codeDepartement":"19","codeRegion":"75","codesPostaux":["19330"],"population":1101},"geometry":{"type":"Point","coordinates":[1.6233154049409209,45.2677780365198]}},{"type":"Feature","properties":{"nom":"Saint-Hilaire-Foissac","code":"19208","codeDepartement":"19","codeRegion":"75","codesPostaux":["19550"],"population":194},"geometry":{"type":"Point","coordinates":[2.1192056266540606,45.3110898516068]}},{"type":"Feature","properties":{"nom":"Saint-Hilaire-les-Courbes","code":"19209","codeDepartement":"19","codeRegion":"75","codesPostaux":["19170"],"population":153},"geometry":{"type":"Point","coordinates":[1.8152260784077205,45.59671115078409]}},{"type":"Feature","properties":{"nom":"Saint-Hilaire-Luc","code":"19210","codeDepartement":"19","codeRegion":"75","codesPostaux":["19160"],"population":71},"geometry":{"type":"Point","coordinates":[2.2065851829268297,45.34619550487803]}},{"type":"Feature","properties":{"nom":"Saint-Hilaire-Peyroux","code":"19211","codeDepartement":"19","codeRegion":"75","codesPostaux":["19560"],"population":966},"geometry":{"type":"Point","coordinates":[1.6389424185185186,45.2117888320988]}},{"type":"Feature","properties":{"nom":"Saint-Hilaire-Taurieux","code":"19212","codeDepartement":"19","codeRegion":"75","codesPostaux":["19400"],"population":99},"geometry":{"type":"Point","coordinates":[1.8349249711538465,45.07842669711536]}},{"type":"Feature","properties":{"nom":"Saint-Jal","code":"19213","codeDepartement":"19","codeRegion":"75","codesPostaux":["19700"],"population":633},"geometry":{"type":"Point","coordinates":[1.6488787608476299,45.39357985267411]}},{"type":"Feature","properties":{"nom":"Saint-Julien-aux-Bois","code":"19214","codeDepartement":"19","codeRegion":"75","codesPostaux":["19220"],"population":466},"geometry":{"type":"Point","coordinates":[2.1483087054455443,45.1275681955445]}},{"type":"Feature","properties":{"nom":"Saint-Julien-le-Pèlerin","code":"19215","codeDepartement":"19","codeRegion":"75","codesPostaux":["19430"],"population":132},"geometry":{"type":"Point","coordinates":[2.0690661287671244,45.00669204657537]}},{"type":"Feature","properties":{"nom":"Saint-Julien-le-Vendômois","code":"19216","codeDepartement":"19","codeRegion":"75","codesPostaux":["19210"],"population":250},"geometry":{"type":"Point","coordinates":[1.3202544385542176,45.456216089156634]}},{"type":"Feature","properties":{"nom":"Saint-Julien-Maumont","code":"19217","codeDepartement":"19","codeRegion":"75","codesPostaux":["19500"],"population":166},"geometry":{"type":"Point","coordinates":[1.7071929866071425,45.03450061607146]}},{"type":"Feature","properties":{"nom":"Sainte-Marie-Lapanouze","code":"19219","codeDepartement":"19","codeRegion":"75","codesPostaux":["19160"],"population":63},"geometry":{"type":"Point","coordinates":[2.3443907061403495,45.43321889035085]}},{"type":"Feature","properties":{"nom":"Saint-Martial-de-Gimel","code":"19220","codeDepartement":"19","codeRegion":"75","codesPostaux":["19150"],"population":488},"geometry":{"type":"Point","coordinates":[1.8866084963017749,45.270093388313576]}},{"type":"Feature","properties":{"nom":"Saint-Martial-Entraygues","code":"19221","codeDepartement":"19","codeRegion":"75","codesPostaux":["19400"],"population":82},"geometry":{"type":"Point","coordinates":[1.9678038098159525,45.13048534049079]}},{"type":"Feature","properties":{"nom":"Saint-Martin-la-Méanne","code":"19222","codeDepartement":"19","codeRegion":"75","codesPostaux":["19320"],"population":340},"geometry":{"type":"Point","coordinates":[1.9909055057766365,45.17067155712444]}},{"type":"Feature","properties":{"nom":"Saint-Martin-Sepert","code":"19223","codeDepartement":"19","codeRegion":"75","codesPostaux":["19210"],"population":283},"geometry":{"type":"Point","coordinates":[1.480469073584906,45.44238659245282]}},{"type":"Feature","properties":{"nom":"Saint-Merd-de-Lapleau","code":"19225","codeDepartement":"19","codeRegion":"75","codesPostaux":["19320"],"population":183},"geometry":{"type":"Point","coordinates":[2.099680730094464,45.25202819028341]}},{"type":"Feature","properties":{"nom":"Saint-Merd-les-Oussines","code":"19226","codeDepartement":"19","codeRegion":"75","codesPostaux":["19170"],"population":130},"geometry":{"type":"Point","coordinates":[2.0300601661538455,45.616627323076976]}},{"type":"Feature","properties":{"nom":"Saint-Mexant","code":"19227","codeDepartement":"19","codeRegion":"75","codesPostaux":["19330"],"population":1309},"geometry":{"type":"Point","coordinates":[1.6740479533502994,45.292215184902446]}},{"type":"Feature","properties":{"nom":"Saint-Pantaléon-de-Lapleau","code":"19228","codeDepartement":"19","codeRegion":"75","codesPostaux":["19160"],"population":67},"geometry":{"type":"Point","coordinates":[2.2013766532951315,45.318706914040135]}},{"type":"Feature","properties":{"nom":"Saint-Pantaléon-de-Larche","code":"19229","codeDepartement":"19","codeRegion":"75","codesPostaux":["19600"],"population":4787},"geometry":{"type":"Point","coordinates":[1.4325208052550236,45.149830057187]}},{"type":"Feature","properties":{"nom":"Saint-Pardoux-Corbier","code":"19230","codeDepartement":"19","codeRegion":"75","codesPostaux":["19210"],"population":417},"geometry":{"type":"Point","coordinates":[1.4562576350974916,45.45047447910858]}},{"type":"Feature","properties":{"nom":"Saint-Pardoux-la-Croisille","code":"19231","codeDepartement":"19","codeRegion":"75","codesPostaux":["19320"],"population":176},"geometry":{"type":"Point","coordinates":[1.976208360330582,45.24802930413222]}},{"type":"Feature","properties":{"nom":"Saint-Pardoux-le-Neuf","code":"19232","codeDepartement":"19","codeRegion":"75","codesPostaux":["19200"],"population":78},"geometry":{"type":"Point","coordinates":[2.3270547162629747,45.60877066435986]}},{"type":"Feature","properties":{"nom":"Saint-Pardoux-le-Vieux","code":"19233","codeDepartement":"19","codeRegion":"75","codesPostaux":["19200"],"population":299},"geometry":{"type":"Point","coordinates":[2.273207281690141,45.596165482394355]}},{"type":"Feature","properties":{"nom":"Saint-Pardoux-l'Ortigier","code":"19234","codeDepartement":"19","codeRegion":"75","codesPostaux":["19270"],"population":480},"geometry":{"type":"Point","coordinates":[1.5845602601476023,45.29962118265686]}},{"type":"Feature","properties":{"nom":"Saint-Paul","code":"19235","codeDepartement":"19","codeRegion":"75","codesPostaux":["19150"],"population":212},"geometry":{"type":"Point","coordinates":[1.8964327785234885,45.205769419463124]}},{"type":"Feature","properties":{"nom":"Saint-Priest-de-Gimel","code":"19236","codeDepartement":"19","codeRegion":"75","codesPostaux":["19800"],"population":496},"geometry":{"type":"Point","coordinates":[1.9002916562499994,45.301576185855254]}},{"type":"Feature","properties":{"nom":"Saint-Privat","code":"19237","codeDepartement":"19","codeRegion":"75","codesPostaux":["19220"],"population":1081},"geometry":{"type":"Point","coordinates":[2.0835436867321855,45.140898900491365]}},{"type":"Feature","properties":{"nom":"Saint-Rémy","code":"19238","codeDepartement":"19","codeRegion":"75","codesPostaux":["19290"],"population":224},"geometry":{"type":"Point","coordinates":[2.2674706186440683,45.660846980932185]}},{"type":"Feature","properties":{"nom":"Saint-Robert","code":"19239","codeDepartement":"19","codeRegion":"75","codesPostaux":["19310"],"population":312},"geometry":{"type":"Point","coordinates":[1.298899104918033,45.25378849508198]}},{"type":"Feature","properties":{"nom":"Saint-Salvadour","code":"19240","codeDepartement":"19","codeRegion":"75","codesPostaux":["19700"],"population":310},"geometry":{"type":"Point","coordinates":[1.7666516954102927,45.3883323171071]}},{"type":"Feature","properties":{"nom":"Saint-Setiers","code":"19241","codeDepartement":"19","codeRegion":"75","codesPostaux":["19290"],"population":283},"geometry":{"type":"Point","coordinates":[2.1226056125419923,45.69672355767075]}},{"type":"Feature","properties":{"nom":"Saint-Solve","code":"19242","codeDepartement":"19","codeRegion":"75","codesPostaux":["19130"],"population":461},"geometry":{"type":"Point","coordinates":[1.4034038872403551,45.306369332344204]}},{"type":"Feature","properties":{"nom":"Saint-Sornin-Lavolps","code":"19243","codeDepartement":"19","codeRegion":"75","codesPostaux":["19230"],"population":864},"geometry":{"type":"Point","coordinates":[1.3701614441860464,45.3700614093023]}},{"type":"Feature","properties":{"nom":"Saint-Sulpice-les-Bois","code":"19244","codeDepartement":"19","codeRegion":"75","codesPostaux":["19250"],"population":84},"geometry":{"type":"Point","coordinates":[2.144787634382565,45.60934067070214]}},{"type":"Feature","properties":{"nom":"Saint-Sylvain","code":"19245","codeDepartement":"19","codeRegion":"75","codesPostaux":["19380"],"population":136},"geometry":{"type":"Point","coordinates":[1.8844610831509832,45.180523975930015]}},{"type":"Feature","properties":{"nom":"Saint-Viance","code":"19246","codeDepartement":"19","codeRegion":"75","codesPostaux":["19240"],"population":1823},"geometry":{"type":"Point","coordinates":[1.4652592755632587,45.20885505719235]}},{"type":"Feature","properties":{"nom":"Saint-Victour","code":"19247","codeDepartement":"19","codeRegion":"75","codesPostaux":["19200"],"population":181},"geometry":{"type":"Point","coordinates":[2.3930392010869563,45.46595346739132]}},{"type":"Feature","properties":{"nom":"Saint-Ybard","code":"19248","codeDepartement":"19","codeRegion":"75","codesPostaux":["19140"],"population":681},"geometry":{"type":"Point","coordinates":[1.5142847087719318,45.45650762339174]}},{"type":"Feature","properties":{"nom":"Saint-Yrieix-le-Déjalat","code":"19249","codeDepartement":"19","codeRegion":"75","codesPostaux":["19300"],"population":345},"geometry":{"type":"Point","coordinates":[1.9673937408207338,45.45743502483802]}},{"type":"Feature","properties":{"nom":"Salon-la-Tour","code":"19250","codeDepartement":"19","codeRegion":"75","codesPostaux":["19510"],"population":652},"geometry":{"type":"Point","coordinates":[1.5311128721668184,45.49771254397095]}},{"type":"Feature","properties":{"nom":"Sarran","code":"19251","codeDepartement":"19","codeRegion":"75","codesPostaux":["19800"],"population":275},"geometry":{"type":"Point","coordinates":[1.9294283502906964,45.41217646947672]}},{"type":"Feature","properties":{"nom":"Sarroux - Saint Julien","code":"19252","codeDepartement":"19","codeRegion":"75","codesPostaux":["19110"],"population":842},"geometry":{"type":"Point","coordinates":[2.4447192183288404,45.436179475741234]}},{"type":"Feature","properties":{"nom":"Segonzac","code":"19253","codeDepartement":"19","codeRegion":"75","codesPostaux":["19310"],"population":224},"geometry":{"type":"Point","coordinates":[1.2670656037735863,45.27950270283022]}},{"type":"Feature","properties":{"nom":"Ségur-le-Château","code":"19254","codeDepartement":"19","codeRegion":"75","codesPostaux":["19230"],"population":179},"geometry":{"type":"Point","coordinates":[1.2975068787234036,45.43020744468089]}},{"type":"Feature","properties":{"nom":"Seilhac","code":"19255","codeDepartement":"19","codeRegion":"75","codesPostaux":["19700"],"population":1719},"geometry":{"type":"Point","coordinates":[1.7211599599666396,45.36531359216017]}},{"type":"Feature","properties":{"nom":"Sérandon","code":"19256","codeDepartement":"19","codeRegion":"75","codesPostaux":["19160"],"population":357},"geometry":{"type":"Point","coordinates":[2.3135538463302767,45.35497638073397]}},{"type":"Feature","properties":{"nom":"Sérilhac","code":"19257","codeDepartement":"19","codeRegion":"75","codesPostaux":["19190"],"population":268},"geometry":{"type":"Point","coordinates":[1.7342386403669718,45.097778970642175]}},{"type":"Feature","properties":{"nom":"Servières-le-Château","code":"19258","codeDepartement":"19","codeRegion":"75","codesPostaux":["19220"],"population":616},"geometry":{"type":"Point","coordinates":[2.0227507317518247,45.14327717518245]}},{"type":"Feature","properties":{"nom":"Sexcles","code":"19259","codeDepartement":"19","codeRegion":"75","codesPostaux":["19430"],"population":234},"geometry":{"type":"Point","coordinates":[2.016420096370462,45.03696244180229]}},{"type":"Feature","properties":{"nom":"Sioniac","code":"19260","codeDepartement":"19","codeRegion":"75","codesPostaux":["19120"],"population":229},"geometry":{"type":"Point","coordinates":[1.7998889018404898,44.97527088343562]}},{"type":"Feature","properties":{"nom":"Sornac","code":"19261","codeDepartement":"19","codeRegion":"75","codesPostaux":["19290"],"population":767},"geometry":{"type":"Point","coordinates":[2.1826517232704394,45.671106681042225]}},{"type":"Feature","properties":{"nom":"Soudaine-Lavinadière","code":"19262","codeDepartement":"19","codeRegion":"75","codesPostaux":["19370"],"population":176},"geometry":{"type":"Point","coordinates":[1.7311916809605477,45.544282108061786]}},{"type":"Feature","properties":{"nom":"Soudeilles","code":"19263","codeDepartement":"19","codeRegion":"75","codesPostaux":["19300"],"population":306},"geometry":{"type":"Point","coordinates":[2.0634714304932755,45.44477055381167]}},{"type":"Feature","properties":{"nom":"Soursac","code":"19264","codeDepartement":"19","codeRegion":"75","codesPostaux":["19550"],"population":502},"geometry":{"type":"Point","coordinates":[2.1923837895595453,45.26525962479601]}},{"type":"Feature","properties":{"nom":"Tarnac","code":"19265","codeDepartement":"19","codeRegion":"75","codesPostaux":["19170"],"population":327},"geometry":{"type":"Point","coordinates":[1.956446039638387,45.67706970027819]}},{"type":"Feature","properties":{"nom":"Thalamy","code":"19266","codeDepartement":"19","codeRegion":"75","codesPostaux":["19200"],"population":96},"geometry":{"type":"Point","coordinates":[2.4600894973684206,45.50746499736842]}},{"type":"Feature","properties":{"nom":"Toy-Viam","code":"19268","codeDepartement":"19","codeRegion":"75","codesPostaux":["19170"],"population":37},"geometry":{"type":"Point","coordinates":[1.9348561231527086,45.64834158128077]}},{"type":"Feature","properties":{"nom":"Treignac","code":"19269","codeDepartement":"19","codeRegion":"75","codesPostaux":["19260"],"population":1356},"geometry":{"type":"Point","coordinates":[1.7946599591836725,45.55744409603843]}},{"type":"Feature","properties":{"nom":"Troche","code":"19270","codeDepartement":"19","codeRegion":"75","codesPostaux":["19230"],"population":560},"geometry":{"type":"Point","coordinates":[1.4546200963244593,45.39351768314321]}},{"type":"Feature","properties":{"nom":"Tudeils","code":"19271","codeDepartement":"19","codeRegion":"75","codesPostaux":["19120"],"population":245},"geometry":{"type":"Point","coordinates":[1.7824878062200962,45.04878726794256]}},{"type":"Feature","properties":{"nom":"Tulle","code":"19272","codeDepartement":"19","codeRegion":"75","codesPostaux":["19000"],"population":14453},"geometry":{"type":"Point","coordinates":[1.7597034359526358,45.274380687836356]}},{"type":"Feature","properties":{"nom":"Turenne","code":"19273","codeDepartement":"19","codeRegion":"75","codesPostaux":["19500"],"population":850},"geometry":{"type":"Point","coordinates":[1.5797799503311256,45.06678110706397]}},{"type":"Feature","properties":{"nom":"Ussac","code":"19274","codeDepartement":"19","codeRegion":"75","codesPostaux":["19270"],"population":4169},"geometry":{"type":"Point","coordinates":[1.5161798248009088,45.19049790671217]}},{"type":"Feature","properties":{"nom":"Ussel","code":"19275","codeDepartement":"19","codeRegion":"75","codesPostaux":["19200"],"population":9782},"geometry":{"type":"Point","coordinates":[2.3033162252100854,45.55341247899166]}},{"type":"Feature","properties":{"nom":"Uzerche","code":"19276","codeDepartement":"19","codeRegion":"75","codesPostaux":["19140"],"population":2848},"geometry":{"type":"Point","coordinates":[1.568928611320756,45.43204054339622]}},{"type":"Feature","properties":{"nom":"Valiergues","code":"19277","codeDepartement":"19","codeRegion":"75","codesPostaux":["19200"],"population":145},"geometry":{"type":"Point","coordinates":[2.2868980305810394,45.47717830275228]}},{"type":"Feature","properties":{"nom":"Varetz","code":"19278","codeDepartement":"19","codeRegion":"75","codesPostaux":["19240"],"population":2407},"geometry":{"type":"Point","coordinates":[1.434585190476192,45.1893019392447]}},{"type":"Feature","properties":{"nom":"Vars-sur-Roseix","code":"19279","codeDepartement":"19","codeRegion":"75","codesPostaux":["19130"],"population":375},"geometry":{"type":"Point","coordinates":[1.3740290519480522,45.26211007359308]}},{"type":"Feature","properties":{"nom":"Végennes","code":"19280","codeDepartement":"19","codeRegion":"75","codesPostaux":["19120"],"population":176},"geometry":{"type":"Point","coordinates":[1.748828164179105,44.980530260127914]}},{"type":"Feature","properties":{"nom":"Veix","code":"19281","codeDepartement":"19","codeRegion":"75","codesPostaux":["19260"],"population":65},"geometry":{"type":"Point","coordinates":[1.8390825978260867,45.50177360869567]}},{"type":"Feature","properties":{"nom":"Veyrières","code":"19283","codeDepartement":"19","codeRegion":"75","codesPostaux":["19200"],"population":72},"geometry":{"type":"Point","coordinates":[2.394613348242813,45.4903794217252]}},{"type":"Feature","properties":{"nom":"Viam","code":"19284","codeDepartement":"19","codeRegion":"75","codesPostaux":["19170"],"population":100},"geometry":{"type":"Point","coordinates":[1.8847134615384613,45.61065483296703]}},{"type":"Feature","properties":{"nom":"Vigeois","code":"19285","codeDepartement":"19","codeRegion":"75","codesPostaux":["19410"],"population":1202},"geometry":{"type":"Point","coordinates":[1.5087806499013796,45.37919730177513]}},{"type":"Feature","properties":{"nom":"Vignols","code":"19286","codeDepartement":"19","codeRegion":"75","codesPostaux":["19130"],"population":557},"geometry":{"type":"Point","coordinates":[1.4037327234678632,45.32728055904332]}},{"type":"Feature","properties":{"nom":"Vitrac-sur-Montane","code":"19287","codeDepartement":"19","codeRegion":"75","codesPostaux":["19800"],"population":261},"geometry":{"type":"Point","coordinates":[1.9297114568062834,45.37537186780101]}},{"type":"Feature","properties":{"nom":"Voutezac","code":"19288","codeDepartement":"19","codeRegion":"75","codesPostaux":["19130"],"population":1270},"geometry":{"type":"Point","coordinates":[1.4382102903703695,45.291466632592595]}},{"type":"Feature","properties":{"nom":"Yssandon","code":"19289","codeDepartement":"19","codeRegion":"75","codesPostaux":["19310"],"population":684},"geometry":{"type":"Point","coordinates":[1.3861651907131007,45.20347579601991]}}]}