[{"nom":"Solaure en Diois","code":"26001","codeDepartement":"26","codeRegion":"84","codesPostaux":["26150"],"population":457},{"nom":"Albon","code":"26002","codeDepartement":"26","codeRegion":"84","codesPostaux":["26140"],"population":1933},{"nom":"Aleyrac","code":"26003","codeDepartement":"26","codeRegion":"84","codesPostaux":["26770"],"population":46},{"nom":"Alixan","code":"26004","codeDepartement":"26","codeRegion":"84","codesPostaux":["26300"],"population":2497},{"nom":"Allan","code":"26005","codeDepartement":"26","codeRegion":"84","codesPostaux":["26780"],"population":1706},{"nom":"Allex","code":"26006","codeDepartement":"26","codeRegion":"84","codesPostaux":["26400"],"population":2495},{"nom":"Ambonil","code":"26007","codeDepartement":"26","codeRegion":"84","codesPostaux":["26800"],"population":120},{"nom":"Ancône","code":"26008","codeDepartement":"26","codeRegion":"84","codesPostaux":["26200"],"population":1329},{"nom":"Andancette","code":"26009","codeDepartement":"26","codeRegion":"84","codesPostaux":["26140"],"population":1338},{"nom":"Anneyron","code":"26010","codeDepartement":"26","codeRegion":"84","codesPostaux":["26140"],"population":3962},{"nom":"Aouste-sur-Sye","code":"26011","codeDepartement":"26","codeRegion":"84","codesPostaux":["26400"],"population":2495},{"nom":"Arnayon","code":"26012","codeDepartement":"26","codeRegion":"84","codesPostaux":["26470"],"population":26},{"nom":"Arpavon","code":"26013","codeDepartement":"26","codeRegion":"84","codesPostaux":["26110"],"population":77},{"nom":"Arthémonay","code":"26014","codeDepartement":"26","codeRegion":"84","codesPostaux":["26260"],"population":579},{"nom":"Aubenasson","code":"26015","codeDepartement":"26","codeRegion":"84","codesPostaux":["26340"],"population":67},{"nom":"Aubres","code":"26016","codeDepartement":"26","codeRegion":"84","codesPostaux":["26110"],"population":415},{"nom":"Aucelon","code":"26017","codeDepartement":"26","codeRegion":"84","codesPostaux":["26340"],"population":15},{"nom":"Aulan","code":"26018","codeDepartement":"26","codeRegion":"84","codesPostaux":["26570"],"population":11},{"nom":"Aurel","code":"26019","codeDepartement":"26","codeRegion":"84","codesPostaux":["26340"],"population":242},{"nom":"La Répara-Auriples","code":"26020","codeDepartement":"26","codeRegion":"84","codesPostaux":["26400"],"population":230},{"nom":"Autichamp","code":"26021","codeDepartement":"26","codeRegion":"84","codesPostaux":["26400"],"population":119},{"nom":"Ballons","code":"26022","codeDepartement":"26","codeRegion":"84","codesPostaux":["26560"],"population":83},{"nom":"Barbières","code":"26023","codeDepartement":"26","codeRegion":"84","codesPostaux":["26300"],"population":1036},{"nom":"Barcelonne","code":"26024","codeDepartement":"26","codeRegion":"84","codesPostaux":["26120"],"population":349},{"nom":"Barnave","code":"26025","codeDepartement":"26","codeRegion":"84","codesPostaux":["26310"],"population":193},{"nom":"Barret-de-Lioure","code":"26026","codeDepartement":"26","codeRegion":"84","codesPostaux":["26570"],"population":80},{"nom":"Barsac","code":"26027","codeDepartement":"26","codeRegion":"84","codesPostaux":["26150"],"population":139},{"nom":"Bathernay","code":"26028","codeDepartement":"26","codeRegion":"84","codesPostaux":["26260"],"population":249},{"nom":"La Bâtie-des-Fonds","code":"26030","codeDepartement":"26","codeRegion":"84","codesPostaux":["26310"],"population":5},{"nom":"La Bâtie-Rolland","code":"26031","codeDepartement":"26","codeRegion":"84","codesPostaux":["26160"],"population":1001},{"nom":"La Baume-Cornillane","code":"26032","codeDepartement":"26","codeRegion":"84","codesPostaux":["26120"],"population":438},{"nom":"La Baume-de-Transit","code":"26033","codeDepartement":"26","codeRegion":"84","codesPostaux":["26790"],"population":859},{"nom":"La Baume-d'Hostun","code":"26034","codeDepartement":"26","codeRegion":"84","codesPostaux":["26730"],"population":567},{"nom":"Beaufort-sur-Gervanne","code":"26035","codeDepartement":"26","codeRegion":"84","codesPostaux":["26400"],"population":468},{"nom":"Beaumont-en-Diois","code":"26036","codeDepartement":"26","codeRegion":"84","codesPostaux":["26310"],"population":101},{"nom":"Beaumont-lès-Valence","code":"26037","codeDepartement":"26","codeRegion":"84","codesPostaux":["26760"],"population":3670},{"nom":"Beaumont-Monteux","code":"26038","codeDepartement":"26","codeRegion":"84","codesPostaux":["26600"],"population":1304},{"nom":"Beauregard-Baret","code":"26039","codeDepartement":"26","codeRegion":"84","codesPostaux":["26300"],"population":831},{"nom":"Beaurières","code":"26040","codeDepartement":"26","codeRegion":"84","codesPostaux":["26310"],"population":73},{"nom":"Beausemblant","code":"26041","codeDepartement":"26","codeRegion":"84","codesPostaux":["26240"],"population":1434},{"nom":"Beauvallon","code":"26042","codeDepartement":"26","codeRegion":"84","codesPostaux":["26800"],"population":1582},{"nom":"Beauvoisin","code":"26043","codeDepartement":"26","codeRegion":"84","codesPostaux":["26170"],"population":147},{"nom":"La Bégude-de-Mazenc","code":"26045","codeDepartement":"26","codeRegion":"84","codesPostaux":["26160"],"population":1670},{"nom":"Bellecombe-Tarendol","code":"26046","codeDepartement":"26","codeRegion":"84","codesPostaux":["26110"],"population":80},{"nom":"Bellegarde-en-Diois","code":"26047","codeDepartement":"26","codeRegion":"84","codesPostaux":["26470"],"population":83},{"nom":"Bénivay-Ollon","code":"26048","codeDepartement":"26","codeRegion":"84","codesPostaux":["26170"],"population":62},{"nom":"Bésayes","code":"26049","codeDepartement":"26","codeRegion":"84","codesPostaux":["26300"],"population":1204},{"nom":"Bésignan","code":"26050","codeDepartement":"26","codeRegion":"84","codesPostaux":["26110"],"population":76},{"nom":"Bézaudun-sur-Bîne","code":"26051","codeDepartement":"26","codeRegion":"84","codesPostaux":["26460"],"population":72},{"nom":"Bonlieu-sur-Roubion","code":"26052","codeDepartement":"26","codeRegion":"84","codesPostaux":["26160"],"population":467},{"nom":"Bouchet","code":"26054","codeDepartement":"26","codeRegion":"84","codesPostaux":["26790"],"population":1499},{"nom":"Boulc","code":"26055","codeDepartement":"26","codeRegion":"84","codesPostaux":["26410"],"population":126},{"nom":"Bourdeaux","code":"26056","codeDepartement":"26","codeRegion":"84","codesPostaux":["26460"],"population":639},{"nom":"Bourg-de-Péage","code":"26057","codeDepartement":"26","codeRegion":"84","codesPostaux":["26300"],"population":10498},{"nom":"Bourg-lès-Valence","code":"26058","codeDepartement":"26","codeRegion":"84","codesPostaux":["26500"],"population":20078},{"nom":"Bouvante","code":"26059","codeDepartement":"26","codeRegion":"84","codesPostaux":["26190"],"population":238},{"nom":"Bouvières","code":"26060","codeDepartement":"26","codeRegion":"84","codesPostaux":["26460"],"population":147},{"nom":"Bren","code":"26061","codeDepartement":"26","codeRegion":"84","codesPostaux":["26260"],"population":557},{"nom":"Brette","code":"26062","codeDepartement":"26","codeRegion":"84","codesPostaux":["26340"],"population":41},{"nom":"Buis-les-Baronnies","code":"26063","codeDepartement":"26","codeRegion":"84","codesPostaux":["26170"],"population":2293},{"nom":"Chabeuil","code":"26064","codeDepartement":"26","codeRegion":"84","codesPostaux":["26120"],"population":6880},{"nom":"Chabrillan","code":"26065","codeDepartement":"26","codeRegion":"84","codesPostaux":["26400"],"population":706},{"nom":"Le Chaffal","code":"26066","codeDepartement":"26","codeRegion":"84","codesPostaux":["26190"],"population":42},{"nom":"Chalancon","code":"26067","codeDepartement":"26","codeRegion":"84","codesPostaux":["26470"],"population":49},{"nom":"Le Chalon","code":"26068","codeDepartement":"26","codeRegion":"84","codesPostaux":["26350"],"population":211},{"nom":"Chamaloc","code":"26069","codeDepartement":"26","codeRegion":"84","codesPostaux":["26150"],"population":131},{"nom":"Chamaret","code":"26070","codeDepartement":"26","codeRegion":"84","codesPostaux":["26230"],"population":561},{"nom":"Chanos-Curson","code":"26071","codeDepartement":"26","codeRegion":"84","codesPostaux":["26600"],"population":1075},{"nom":"Chantemerle-les-Blés","code":"26072","codeDepartement":"26","codeRegion":"84","codesPostaux":["26600"],"population":1278},{"nom":"Chantemerle-lès-Grignan","code":"26073","codeDepartement":"26","codeRegion":"84","codesPostaux":["26230"],"population":261},{"nom":"La Chapelle-en-Vercors","code":"26074","codeDepartement":"26","codeRegion":"84","codesPostaux":["26420"],"population":699},{"nom":"La Charce","code":"26075","codeDepartement":"26","codeRegion":"84","codesPostaux":["26470"],"population":35},{"nom":"Charens","code":"26076","codeDepartement":"26","codeRegion":"84","codesPostaux":["26310"],"population":29},{"nom":"Charmes-sur-l'Herbasse","code":"26077","codeDepartement":"26","codeRegion":"84","codesPostaux":["26260"],"population":934},{"nom":"Charols","code":"26078","codeDepartement":"26","codeRegion":"84","codesPostaux":["26450"],"population":903},{"nom":"Charpey","code":"26079","codeDepartement":"26","codeRegion":"84","codesPostaux":["26300"],"population":1367},{"nom":"Chastel-Arnaud","code":"26080","codeDepartement":"26","codeRegion":"84","codesPostaux":["26340"],"population":38},{"nom":"Châteaudouble","code":"26081","codeDepartement":"26","codeRegion":"84","codesPostaux":["26120"],"population":581},{"nom":"Châteauneuf-de-Bordette","code":"26082","codeDepartement":"26","codeRegion":"84","codesPostaux":["26110"],"population":95},{"nom":"Châteauneuf-de-Galaure","code":"26083","codeDepartement":"26","codeRegion":"84","codesPostaux":["26330"],"population":1792},{"nom":"Châteauneuf-sur-Isère","code":"26084","codeDepartement":"26","codeRegion":"84","codesPostaux":["26300"],"population":3840},{"nom":"Châteauneuf-du-Rhône","code":"26085","codeDepartement":"26","codeRegion":"84","codesPostaux":["26780"],"population":2732},{"nom":"Châtillon-en-Diois","code":"26086","codeDepartement":"26","codeRegion":"84","codesPostaux":["26410"],"population":667},{"nom":"Châtillon-Saint-Jean","code":"26087","codeDepartement":"26","codeRegion":"84","codesPostaux":["26750"],"population":1355},{"nom":"Chatuzange-le-Goubet","code":"26088","codeDepartement":"26","codeRegion":"84","codesPostaux":["26300"],"population":5413},{"nom":"Chaudebonne","code":"26089","codeDepartement":"26","codeRegion":"84","codesPostaux":["26110"],"population":53},{"nom":"La Chaudière","code":"26090","codeDepartement":"26","codeRegion":"84","codesPostaux":["26340"],"population":24},{"nom":"Chauvac-Laux-Montaux","code":"26091","codeDepartement":"26","codeRegion":"84","codesPostaux":["26510"],"population":43},{"nom":"Chavannes","code":"26092","codeDepartement":"26","codeRegion":"84","codesPostaux":["26260"],"population":697},{"nom":"Clansayes","code":"26093","codeDepartement":"26","codeRegion":"84","codesPostaux":["26130"],"population":522},{"nom":"Claveyson","code":"26094","codeDepartement":"26","codeRegion":"84","codesPostaux":["26240"],"population":869},{"nom":"Cléon-d'Andran","code":"26095","codeDepartement":"26","codeRegion":"84","codesPostaux":["26450"],"population":845},{"nom":"Clérieux","code":"26096","codeDepartement":"26","codeRegion":"84","codesPostaux":["26260"],"population":2019},{"nom":"Cliousclat","code":"26097","codeDepartement":"26","codeRegion":"84","codesPostaux":["26270"],"population":643},{"nom":"Cobonne","code":"26098","codeDepartement":"26","codeRegion":"84","codesPostaux":["26400"],"population":163},{"nom":"Colonzelle","code":"26099","codeDepartement":"26","codeRegion":"84","codesPostaux":["26230"],"population":552},{"nom":"Combovin","code":"26100","codeDepartement":"26","codeRegion":"84","codesPostaux":["26120"],"population":409},{"nom":"Comps","code":"26101","codeDepartement":"26","codeRegion":"84","codesPostaux":["26220"],"population":164},{"nom":"Condillac","code":"26102","codeDepartement":"26","codeRegion":"84","codesPostaux":["26740"],"population":141},{"nom":"Condorcet","code":"26103","codeDepartement":"26","codeRegion":"84","codesPostaux":["26110"],"population":480},{"nom":"Cornillac","code":"26104","codeDepartement":"26","codeRegion":"84","codesPostaux":["26510"],"population":81},{"nom":"Cornillon-sur-l'Oule","code":"26105","codeDepartement":"26","codeRegion":"84","codesPostaux":["26510"],"population":69},{"nom":"La Coucourde","code":"26106","codeDepartement":"26","codeRegion":"84","codesPostaux":["26740"],"population":1055},{"nom":"Crépol","code":"26107","codeDepartement":"26","codeRegion":"84","codesPostaux":["26350"],"population":561},{"nom":"Crest","code":"26108","codeDepartement":"26","codeRegion":"84","codesPostaux":["26400"],"population":8380},{"nom":"Crozes-Hermitage","code":"26110","codeDepartement":"26","codeRegion":"84","codesPostaux":["26600"],"population":651},{"nom":"Crupies","code":"26111","codeDepartement":"26","codeRegion":"84","codesPostaux":["26460"],"population":98},{"nom":"Curnier","code":"26112","codeDepartement":"26","codeRegion":"84","codesPostaux":["26110"],"population":172},{"nom":"Die","code":"26113","codeDepartement":"26","codeRegion":"84","codesPostaux":["26150"],"population":4585},{"nom":"Dieulefit","code":"26114","codeDepartement":"26","codeRegion":"84","codesPostaux":["26220"],"population":3121},{"nom":"Divajeu","code":"26115","codeDepartement":"26","codeRegion":"84","codesPostaux":["26400"],"population":637},{"nom":"Donzère","code":"26116","codeDepartement":"26","codeRegion":"84","codesPostaux":["26290"],"population":5739},{"nom":"Échevis","code":"26117","codeDepartement":"26","codeRegion":"84","codesPostaux":["26190"],"population":48},{"nom":"Épinouze","code":"26118","codeDepartement":"26","codeRegion":"84","codesPostaux":["26210"],"population":1558},{"nom":"Érôme","code":"26119","codeDepartement":"26","codeRegion":"84","codesPostaux":["26600"],"population":818},{"nom":"Espeluche","code":"26121","codeDepartement":"26","codeRegion":"84","codesPostaux":["26780"],"population":1039},{"nom":"Espenel","code":"26122","codeDepartement":"26","codeRegion":"84","codesPostaux":["26340"],"population":167},{"nom":"Establet","code":"26123","codeDepartement":"26","codeRegion":"84","codesPostaux":["26470"],"population":28},{"nom":"Étoile-sur-Rhône","code":"26124","codeDepartement":"26","codeRegion":"84","codesPostaux":["26800"],"population":5412},{"nom":"Eurre","code":"26125","codeDepartement":"26","codeRegion":"84","codesPostaux":["26400"],"population":1305},{"nom":"Eygalayes","code":"26126","codeDepartement":"26","codeRegion":"84","codesPostaux":["26560"],"population":84},{"nom":"Eygaliers","code":"26127","codeDepartement":"26","codeRegion":"84","codesPostaux":["26170"],"population":103},{"nom":"Eygluy-Escoulin","code":"26128","codeDepartement":"26","codeRegion":"84","codesPostaux":["26400"],"population":65},{"nom":"Eymeux","code":"26129","codeDepartement":"26","codeRegion":"84","codesPostaux":["26730"],"population":1032},{"nom":"Eyroles","code":"26130","codeDepartement":"26","codeRegion":"84","codesPostaux":["26110"],"population":30},{"nom":"Eyzahut","code":"26131","codeDepartement":"26","codeRegion":"84","codesPostaux":["26160"],"population":142},{"nom":"Fay-le-Clos","code":"26133","codeDepartement":"26","codeRegion":"84","codesPostaux":["26240"],"population":166},{"nom":"Félines-sur-Rimandoule","code":"26134","codeDepartement":"26","codeRegion":"84","codesPostaux":["26160"],"population":76},{"nom":"Ferrassières","code":"26135","codeDepartement":"26","codeRegion":"84","codesPostaux":["26570"],"population":129},{"nom":"Val-Maravel","code":"26136","codeDepartement":"26","codeRegion":"84","codesPostaux":["26310"],"population":57},{"nom":"Francillon-sur-Roubion","code":"26137","codeDepartement":"26","codeRegion":"84","codesPostaux":["26400"],"population":192},{"nom":"La Garde-Adhémar","code":"26138","codeDepartement":"26","codeRegion":"84","codesPostaux":["26700"],"population":1048},{"nom":"Génissieux","code":"26139","codeDepartement":"26","codeRegion":"84","codesPostaux":["26750"],"population":2183},{"nom":"Geyssans","code":"26140","codeDepartement":"26","codeRegion":"84","codesPostaux":["26750"],"population":721},{"nom":"Gigors-et-Lozeron","code":"26141","codeDepartement":"26","codeRegion":"84","codesPostaux":["26400"],"population":178},{"nom":"Glandage","code":"26142","codeDepartement":"26","codeRegion":"84","codesPostaux":["26410"],"population":113},{"nom":"Le Grand-Serre","code":"26143","codeDepartement":"26","codeRegion":"84","codesPostaux":["26530"],"population":907},{"nom":"Grane","code":"26144","codeDepartement":"26","codeRegion":"84","codesPostaux":["26400"],"population":1895},{"nom":"Les Granges-Gontardes","code":"26145","codeDepartement":"26","codeRegion":"84","codesPostaux":["26290"],"population":632},{"nom":"Grignan","code":"26146","codeDepartement":"26","codeRegion":"84","codesPostaux":["26230"],"population":1545},{"nom":"Gumiane","code":"26147","codeDepartement":"26","codeRegion":"84","codesPostaux":["26470"],"population":20},{"nom":"Hauterives","code":"26148","codeDepartement":"26","codeRegion":"84","codesPostaux":["26390"],"population":1900},{"nom":"Hostun","code":"26149","codeDepartement":"26","codeRegion":"84","codesPostaux":["26730"],"population":975},{"nom":"Izon-la-Bruisse","code":"26150","codeDepartement":"26","codeRegion":"84","codesPostaux":["26560"],"population":10},{"nom":"Jonchères","code":"26152","codeDepartement":"26","codeRegion":"84","codesPostaux":["26310"],"population":29},{"nom":"Laborel","code":"26153","codeDepartement":"26","codeRegion":"84","codesPostaux":["26560"],"population":104},{"nom":"Lachau","code":"26154","codeDepartement":"26","codeRegion":"84","codesPostaux":["26560"],"population":228},{"nom":"Lapeyrouse-Mornay","code":"26155","codeDepartement":"26","codeRegion":"84","codesPostaux":["26210"],"population":1217},{"nom":"Larnage","code":"26156","codeDepartement":"26","codeRegion":"84","codesPostaux":["26600"],"population":1073},{"nom":"La Laupie","code":"26157","codeDepartement":"26","codeRegion":"84","codesPostaux":["26740"],"population":774},{"nom":"Laval-d'Aix","code":"26159","codeDepartement":"26","codeRegion":"84","codesPostaux":["26150"],"population":122},{"nom":"Laveyron","code":"26160","codeDepartement":"26","codeRegion":"84","codesPostaux":["26240"],"population":1165},{"nom":"Lemps","code":"26161","codeDepartement":"26","codeRegion":"84","codesPostaux":["26510"],"population":48},{"nom":"Lens-Lestang","code":"26162","codeDepartement":"26","codeRegion":"84","codesPostaux":["26210"],"population":859},{"nom":"Léoncel","code":"26163","codeDepartement":"26","codeRegion":"84","codesPostaux":["26190"],"population":52},{"nom":"Lesches-en-Diois","code":"26164","codeDepartement":"26","codeRegion":"84","codesPostaux":["26310"],"population":50},{"nom":"Livron-sur-Drôme","code":"26165","codeDepartement":"26","codeRegion":"84","codesPostaux":["26250"],"population":9098},{"nom":"Loriol-sur-Drôme","code":"26166","codeDepartement":"26","codeRegion":"84","codesPostaux":["26270"],"population":6561},{"nom":"Luc-en-Diois","code":"26167","codeDepartement":"26","codeRegion":"84","codesPostaux":["26310"],"population":489},{"nom":"Lus-la-Croix-Haute","code":"26168","codeDepartement":"26","codeRegion":"84","codesPostaux":["26620"],"population":549},{"nom":"Malataverne","code":"26169","codeDepartement":"26","codeRegion":"84","codesPostaux":["26780"],"population":1988},{"nom":"Malissard","code":"26170","codeDepartement":"26","codeRegion":"84","codesPostaux":["26120"],"population":3192},{"nom":"Manas","code":"26171","codeDepartement":"26","codeRegion":"84","codesPostaux":["26160"],"population":195},{"nom":"Manthes","code":"26172","codeDepartement":"26","codeRegion":"84","codesPostaux":["26210"],"population":669},{"nom":"Marches","code":"26173","codeDepartement":"26","codeRegion":"84","codesPostaux":["26300"],"population":789},{"nom":"Margès","code":"26174","codeDepartement":"26","codeRegion":"84","codesPostaux":["26260"],"population":1133},{"nom":"Marignac-en-Diois","code":"26175","codeDepartement":"26","codeRegion":"84","codesPostaux":["26150"],"population":208},{"nom":"Marsanne","code":"26176","codeDepartement":"26","codeRegion":"84","codesPostaux":["26740"],"population":1333},{"nom":"Marsaz","code":"26177","codeDepartement":"26","codeRegion":"84","codesPostaux":["26260"],"population":792},{"nom":"Menglon","code":"26178","codeDepartement":"26","codeRegion":"84","codesPostaux":["26410"],"population":501},{"nom":"Mercurol-Veaunes","code":"26179","codeDepartement":"26","codeRegion":"84","codesPostaux":["26600"],"population":2623},{"nom":"Mérindol-les-Oliviers","code":"26180","codeDepartement":"26","codeRegion":"84","codesPostaux":["26170"],"population":229},{"nom":"Mévouillon","code":"26181","codeDepartement":"26","codeRegion":"84","codesPostaux":["26560"],"population":241},{"nom":"Mirabel-aux-Baronnies","code":"26182","codeDepartement":"26","codeRegion":"84","codesPostaux":["26110"],"population":1590},{"nom":"Mirabel-et-Blacons","code":"26183","codeDepartement":"26","codeRegion":"84","codesPostaux":["26400"],"population":1058},{"nom":"Mirmande","code":"26185","codeDepartement":"26","codeRegion":"84","codesPostaux":["26270"],"population":574},{"nom":"Miscon","code":"26186","codeDepartement":"26","codeRegion":"84","codesPostaux":["26310"],"population":56},{"nom":"Mollans-sur-Ouvèze","code":"26188","codeDepartement":"26","codeRegion":"84","codesPostaux":["26170"],"population":1060},{"nom":"Montauban-sur-l'Ouvèze","code":"26189","codeDepartement":"26","codeRegion":"84","codesPostaux":["26170"],"population":109},{"nom":"Montaulieu","code":"26190","codeDepartement":"26","codeRegion":"84","codesPostaux":["26110"],"population":83},{"nom":"Montboucher-sur-Jabron","code":"26191","codeDepartement":"26","codeRegion":"84","codesPostaux":["26740"],"population":2273},{"nom":"Montbrison-sur-Lez","code":"26192","codeDepartement":"26","codeRegion":"84","codesPostaux":["26770"],"population":286},{"nom":"Montbrun-les-Bains","code":"26193","codeDepartement":"26","codeRegion":"84","codesPostaux":["26570"],"population":444},{"nom":"Montchenu","code":"26194","codeDepartement":"26","codeRegion":"84","codesPostaux":["26350"],"population":581},{"nom":"Montclar-sur-Gervanne","code":"26195","codeDepartement":"26","codeRegion":"84","codesPostaux":["26400"],"population":181},{"nom":"Montéléger","code":"26196","codeDepartement":"26","codeRegion":"84","codesPostaux":["26760"],"population":1798},{"nom":"Montélier","code":"26197","codeDepartement":"26","codeRegion":"84","codesPostaux":["26120"],"population":4077},{"nom":"Montélimar","code":"26198","codeDepartement":"26","codeRegion":"84","codesPostaux":["26200"],"population":38692},{"nom":"Montferrand-la-Fare","code":"26199","codeDepartement":"26","codeRegion":"84","codesPostaux":["26510"],"population":30},{"nom":"Montfroc","code":"26200","codeDepartement":"26","codeRegion":"84","codesPostaux":["26560"],"population":75},{"nom":"Montguers","code":"26201","codeDepartement":"26","codeRegion":"84","codesPostaux":["26170"],"population":43},{"nom":"Montjoux","code":"26202","codeDepartement":"26","codeRegion":"84","codesPostaux":["26220"],"population":339},{"nom":"Montjoyer","code":"26203","codeDepartement":"26","codeRegion":"84","codesPostaux":["26230"],"population":279},{"nom":"Montlaur-en-Diois","code":"26204","codeDepartement":"26","codeRegion":"84","codesPostaux":["26310"],"population":149},{"nom":"Montmaur-en-Diois","code":"26205","codeDepartement":"26","codeRegion":"84","codesPostaux":["26150"],"population":82},{"nom":"Montmeyran","code":"26206","codeDepartement":"26","codeRegion":"84","codesPostaux":["26120"],"population":2877},{"nom":"Montmiral","code":"26207","codeDepartement":"26","codeRegion":"84","codesPostaux":["26750"],"population":660},{"nom":"Montoison","code":"26208","codeDepartement":"26","codeRegion":"84","codesPostaux":["26800"],"population":1912},{"nom":"Montréal-les-Sources","code":"26209","codeDepartement":"26","codeRegion":"84","codesPostaux":["26510"],"population":24},{"nom":"Valherbasse","code":"26210","codeDepartement":"26","codeRegion":"84","codesPostaux":["26350"],"population":1002},{"nom":"Montségur-sur-Lauzon","code":"26211","codeDepartement":"26","codeRegion":"84","codesPostaux":["26130"],"population":1291},{"nom":"Montvendre","code":"26212","codeDepartement":"26","codeRegion":"84","codesPostaux":["26120"],"population":1167},{"nom":"Moras-en-Valloire","code":"26213","codeDepartement":"26","codeRegion":"84","codesPostaux":["26210"],"population":657},{"nom":"Mornans","code":"26214","codeDepartement":"26","codeRegion":"84","codesPostaux":["26460"],"population":70},{"nom":"La Motte-Chalancon","code":"26215","codeDepartement":"26","codeRegion":"84","codesPostaux":["26470"],"population":427},{"nom":"La Motte-de-Galaure","code":"26216","codeDepartement":"26","codeRegion":"84","codesPostaux":["26240"],"population":790},{"nom":"La Motte-Fanjas","code":"26217","codeDepartement":"26","codeRegion":"84","codesPostaux":["26190"],"population":190},{"nom":"Mours-Saint-Eusèbe","code":"26218","codeDepartement":"26","codeRegion":"84","codesPostaux":["26540"],"population":3096},{"nom":"Mureils","code":"26219","codeDepartement":"26","codeRegion":"84","codesPostaux":["26240"],"population":465},{"nom":"Nyons","code":"26220","codeDepartement":"26","codeRegion":"84","codesPostaux":["26110"],"population":6742},{"nom":"Omblèze","code":"26221","codeDepartement":"26","codeRegion":"84","codesPostaux":["26400"],"population":71},{"nom":"Orcinas","code":"26222","codeDepartement":"26","codeRegion":"84","codesPostaux":["26220"],"population":38},{"nom":"Oriol-en-Royans","code":"26223","codeDepartement":"26","codeRegion":"84","codesPostaux":["26190"],"population":536},{"nom":"Ourches","code":"26224","codeDepartement":"26","codeRegion":"84","codesPostaux":["26120"],"population":247},{"nom":"Parnans","code":"26225","codeDepartement":"26","codeRegion":"84","codesPostaux":["26750"],"population":699},{"nom":"Le Pègue","code":"26226","codeDepartement":"26","codeRegion":"84","codesPostaux":["26770"],"population":362},{"nom":"Pelonne","code":"26227","codeDepartement":"26","codeRegion":"84","codesPostaux":["26510"],"population":23},{"nom":"Pennes-le-Sec","code":"26228","codeDepartement":"26","codeRegion":"84","codesPostaux":["26340"],"population":34},{"nom":"La Penne-sur-l'Ouvèze","code":"26229","codeDepartement":"26","codeRegion":"84","codesPostaux":["26170"],"population":99},{"nom":"Peyrins","code":"26231","codeDepartement":"26","codeRegion":"84","codesPostaux":["26380"],"population":2802},{"nom":"Peyrus","code":"26232","codeDepartement":"26","codeRegion":"84","codesPostaux":["26120"],"population":605},{"nom":"Piégon","code":"26233","codeDepartement":"26","codeRegion":"84","codesPostaux":["26110"],"population":269},{"nom":"Piégros-la-Clastre","code":"26234","codeDepartement":"26","codeRegion":"84","codesPostaux":["26400"],"population":825},{"nom":"Pierrelatte","code":"26235","codeDepartement":"26","codeRegion":"84","codesPostaux":["26700"],"population":13286},{"nom":"Pierrelongue","code":"26236","codeDepartement":"26","codeRegion":"84","codesPostaux":["26170"],"population":220},{"nom":"Les Pilles","code":"26238","codeDepartement":"26","codeRegion":"84","codesPostaux":["26110"],"population":246},{"nom":"Plaisians","code":"26239","codeDepartement":"26","codeRegion":"84","codesPostaux":["26170"],"population":197},{"nom":"Plan-de-Baix","code":"26240","codeDepartement":"26","codeRegion":"84","codesPostaux":["26400"],"population":145},{"nom":"Le Poët-Célard","code":"26241","codeDepartement":"26","codeRegion":"84","codesPostaux":["26460"],"population":126},{"nom":"Le Poët-en-Percip","code":"26242","codeDepartement":"26","codeRegion":"84","codesPostaux":["26170"],"population":17},{"nom":"Le Poët-Laval","code":"26243","codeDepartement":"26","codeRegion":"84","codesPostaux":["26160"],"population":923},{"nom":"Le Poët-Sigillat","code":"26244","codeDepartement":"26","codeRegion":"84","codesPostaux":["26110"],"population":119},{"nom":"Pommerol","code":"26245","codeDepartement":"26","codeRegion":"84","codesPostaux":["26470"],"population":15},{"nom":"Ponet-et-Saint-Auban","code":"26246","codeDepartement":"26","codeRegion":"84","codesPostaux":["26150"],"population":126},{"nom":"Ponsas","code":"26247","codeDepartement":"26","codeRegion":"84","codesPostaux":["26240"],"population":521},{"nom":"Pontaix","code":"26248","codeDepartement":"26","codeRegion":"84","codesPostaux":["26150"],"population":166},{"nom":"Pont-de-Barret","code":"26249","codeDepartement":"26","codeRegion":"84","codesPostaux":["26160"],"population":671},{"nom":"Pont-de-l'Isère","code":"26250","codeDepartement":"26","codeRegion":"84","codesPostaux":["26600"],"population":3415},{"nom":"Portes-en-Valdaine","code":"26251","codeDepartement":"26","codeRegion":"84","codesPostaux":["26160"],"population":397},{"nom":"Portes-lès-Valence","code":"26252","codeDepartement":"26","codeRegion":"84","codesPostaux":["26800"],"population":10445},{"nom":"Poyols","code":"26253","codeDepartement":"26","codeRegion":"84","codesPostaux":["26310"],"population":69},{"nom":"Pradelle","code":"26254","codeDepartement":"26","codeRegion":"84","codesPostaux":["26340"],"population":18},{"nom":"Les Prés","code":"26255","codeDepartement":"26","codeRegion":"84","codesPostaux":["26310"],"population":23},{"nom":"Propiac","code":"26256","codeDepartement":"26","codeRegion":"84","codesPostaux":["26170"],"population":124},{"nom":"Puygiron","code":"26257","codeDepartement":"26","codeRegion":"84","codesPostaux":["26160"],"population":421},{"nom":"Puy-Saint-Martin","code":"26258","codeDepartement":"26","codeRegion":"84","codesPostaux":["26450"],"population":881},{"nom":"Ratières","code":"26259","codeDepartement":"26","codeRegion":"84","codesPostaux":["26330"],"population":270},{"nom":"Réauville","code":"26261","codeDepartement":"26","codeRegion":"84","codesPostaux":["26230"],"population":383},{"nom":"Recoubeau-Jansac","code":"26262","codeDepartement":"26","codeRegion":"84","codesPostaux":["26310"],"population":271},{"nom":"Reilhanette","code":"26263","codeDepartement":"26","codeRegion":"84","codesPostaux":["26570"],"population":144},{"nom":"Rémuzat","code":"26264","codeDepartement":"26","codeRegion":"84","codesPostaux":["26510"],"population":352},{"nom":"Rimon-et-Savel","code":"26266","codeDepartement":"26","codeRegion":"84","codesPostaux":["26340"],"population":28},{"nom":"Rioms","code":"26267","codeDepartement":"26","codeRegion":"84","codesPostaux":["26170"],"population":26},{"nom":"Rochebaudin","code":"26268","codeDepartement":"26","codeRegion":"84","codesPostaux":["26160"],"population":121},{"nom":"Rochebrune","code":"26269","codeDepartement":"26","codeRegion":"84","codesPostaux":["26110"],"population":63},{"nom":"Rochechinard","code":"26270","codeDepartement":"26","codeRegion":"84","codesPostaux":["26190"],"population":115},{"nom":"La Roche-de-Glun","code":"26271","codeDepartement":"26","codeRegion":"84","codesPostaux":["26600"],"population":3280},{"nom":"Rochefort-en-Valdaine","code":"26272","codeDepartement":"26","codeRegion":"84","codesPostaux":["26160"],"population":352},{"nom":"Rochefort-Samson","code":"26273","codeDepartement":"26","codeRegion":"84","codesPostaux":["26300"],"population":1000},{"nom":"Rochefourchat","code":"26274","codeDepartement":"26","codeRegion":"84","codesPostaux":["26340"],"population":1},{"nom":"Rochegude","code":"26275","codeDepartement":"26","codeRegion":"84","codesPostaux":["26790"],"population":1586},{"nom":"Roche-Saint-Secret-Béconne","code":"26276","codeDepartement":"26","codeRegion":"84","codesPostaux":["26770"],"population":446},{"nom":"La Roche-sur-Grane","code":"26277","codeDepartement":"26","codeRegion":"84","codesPostaux":["26400"],"population":174},{"nom":"La Roche-sur-le-Buis","code":"26278","codeDepartement":"26","codeRegion":"84","codesPostaux":["26170"],"population":292},{"nom":"La Rochette-du-Buis","code":"26279","codeDepartement":"26","codeRegion":"84","codesPostaux":["26170"],"population":78},{"nom":"Romans-sur-Isère","code":"26281","codeDepartement":"26","codeRegion":"84","codesPostaux":["26100"],"population":33310},{"nom":"Romeyer","code":"26282","codeDepartement":"26","codeRegion":"84","codesPostaux":["26150"],"population":198},{"nom":"Rottier","code":"26283","codeDepartement":"26","codeRegion":"84","codesPostaux":["26470"],"population":21},{"nom":"Roussas","code":"26284","codeDepartement":"26","codeRegion":"84","codesPostaux":["26230"],"population":365},{"nom":"Rousset-les-Vignes","code":"26285","codeDepartement":"26","codeRegion":"84","codesPostaux":["26770"],"population":293},{"nom":"Roussieux","code":"26286","codeDepartement":"26","codeRegion":"84","codesPostaux":["26510"],"population":23},{"nom":"Roynac","code":"26287","codeDepartement":"26","codeRegion":"84","codesPostaux":["26450"],"population":484},{"nom":"Sahune","code":"26288","codeDepartement":"26","codeRegion":"84","codesPostaux":["26510"],"population":315},{"nom":"Saillans","code":"26289","codeDepartement":"26","codeRegion":"84","codesPostaux":["26340"],"population":1233},{"nom":"Saint-Agnan-en-Vercors","code":"26290","codeDepartement":"26","codeRegion":"84","codesPostaux":["26420"],"population":387},{"nom":"Saint-Andéol","code":"26291","codeDepartement":"26","codeRegion":"84","codesPostaux":["26150"],"population":80},{"nom":"Saint-Auban-sur-l'Ouvèze","code":"26292","codeDepartement":"26","codeRegion":"84","codesPostaux":["26170"],"population":215},{"nom":"Saint-Avit","code":"26293","codeDepartement":"26","codeRegion":"84","codesPostaux":["26330"],"population":302},{"nom":"Saint-Bardoux","code":"26294","codeDepartement":"26","codeRegion":"84","codesPostaux":["26260"],"population":607},{"nom":"Saint-Barthélemy-de-Vals","code":"26295","codeDepartement":"26","codeRegion":"84","codesPostaux":["26240"],"population":1884},{"nom":"Saint-Benoit-en-Diois","code":"26296","codeDepartement":"26","codeRegion":"84","codesPostaux":["26340"],"population":26},{"nom":"Saint-Christophe-et-le-Laris","code":"26298","codeDepartement":"26","codeRegion":"84","codesPostaux":["26350"],"population":411},{"nom":"Sainte-Croix","code":"26299","codeDepartement":"26","codeRegion":"84","codesPostaux":["26150"],"population":107},{"nom":"Saint-Dizier-en-Diois","code":"26300","codeDepartement":"26","codeRegion":"84","codesPostaux":["26310"],"population":48},{"nom":"Saint-Donat-sur-l'Herbasse","code":"26301","codeDepartement":"26","codeRegion":"84","codesPostaux":["26260"],"population":4107},{"nom":"Sainte-Eulalie-en-Royans","code":"26302","codeDepartement":"26","codeRegion":"84","codesPostaux":["26190"],"population":540},{"nom":"Sainte-Euphémie-sur-Ouvèze","code":"26303","codeDepartement":"26","codeRegion":"84","codesPostaux":["26170"],"population":71},{"nom":"Saint-Ferréol-Trente-Pas","code":"26304","codeDepartement":"26","codeRegion":"84","codesPostaux":["26110"],"population":248},{"nom":"Saint-Gervais-sur-Roubion","code":"26305","codeDepartement":"26","codeRegion":"84","codesPostaux":["26160"],"population":1000},{"nom":"Sainte-Jalle","code":"26306","codeDepartement":"26","codeRegion":"84","codesPostaux":["26110"],"population":304},{"nom":"Saint-Jean-en-Royans","code":"26307","codeDepartement":"26","codeRegion":"84","codesPostaux":["26190"],"population":2918},{"nom":"Saint-Julien-en-Quint","code":"26308","codeDepartement":"26","codeRegion":"84","codesPostaux":["26150"],"population":155},{"nom":"Saint-Julien-en-Vercors","code":"26309","codeDepartement":"26","codeRegion":"84","codesPostaux":["26420"],"population":242},{"nom":"Saint-Laurent-d'Onay","code":"26310","codeDepartement":"26","codeRegion":"84","codesPostaux":["26350"],"population":152},{"nom":"Saint-Laurent-en-Royans","code":"26311","codeDepartement":"26","codeRegion":"84","codesPostaux":["26190"],"population":1391},{"nom":"Saint-Marcel-lès-Sauzet","code":"26312","codeDepartement":"26","codeRegion":"84","codesPostaux":["26740"],"population":1247},{"nom":"Saint-Marcel-lès-Valence","code":"26313","codeDepartement":"26","codeRegion":"84","codesPostaux":["26320"],"population":6201},{"nom":"Saint-Martin-d'Août","code":"26314","codeDepartement":"26","codeRegion":"84","codesPostaux":["26330"],"population":382},{"nom":"Saint-Martin-en-Vercors","code":"26315","codeDepartement":"26","codeRegion":"84","codesPostaux":["26420"],"population":371},{"nom":"Saint-Martin-le-Colonel","code":"26316","codeDepartement":"26","codeRegion":"84","codesPostaux":["26190"],"population":190},{"nom":"Saint-Maurice-sur-Eygues","code":"26317","codeDepartement":"26","codeRegion":"84","codesPostaux":["26110"],"population":771},{"nom":"Saint-May","code":"26318","codeDepartement":"26","codeRegion":"84","codesPostaux":["26510"],"population":41},{"nom":"Saint-Michel-sur-Savasse","code":"26319","codeDepartement":"26","codeRegion":"84","codesPostaux":["26750"],"population":574},{"nom":"Saint-Nazaire-en-Royans","code":"26320","codeDepartement":"26","codeRegion":"84","codesPostaux":["26190"],"population":799},{"nom":"Saint-Nazaire-le-Désert","code":"26321","codeDepartement":"26","codeRegion":"84","codesPostaux":["26340"],"population":190},{"nom":"Saint-Pantaléon-les-Vignes","code":"26322","codeDepartement":"26","codeRegion":"84","codesPostaux":["26770"],"population":445},{"nom":"Saint-Paul-lès-Romans","code":"26323","codeDepartement":"26","codeRegion":"84","codesPostaux":["26750"],"population":1822},{"nom":"Saint-Paul-Trois-Châteaux","code":"26324","codeDepartement":"26","codeRegion":"84","codesPostaux":["26130"],"population":9026},{"nom":"Saint-Rambert-d'Albon","code":"26325","codeDepartement":"26","codeRegion":"84","codesPostaux":["26140"],"population":6420},{"nom":"Saint-Restitut","code":"26326","codeDepartement":"26","codeRegion":"84","codesPostaux":["26130"],"population":1373},{"nom":"Saint-Roman","code":"26327","codeDepartement":"26","codeRegion":"84","codesPostaux":["26410"],"population":189},{"nom":"Saint-Sauveur-en-Diois","code":"26328","codeDepartement":"26","codeRegion":"84","codesPostaux":["26340"],"population":55},{"nom":"Saint-Sauveur-Gouvernet","code":"26329","codeDepartement":"26","codeRegion":"84","codesPostaux":["26110"],"population":183},{"nom":"Saint-Sorlin-en-Valloire","code":"26330","codeDepartement":"26","codeRegion":"84","codesPostaux":["26210"],"population":2250},{"nom":"Saint-Thomas-en-Royans","code":"26331","codeDepartement":"26","codeRegion":"84","codesPostaux":["26190"],"population":591},{"nom":"Saint-Uze","code":"26332","codeDepartement":"26","codeRegion":"84","codesPostaux":["26240"],"population":2040},{"nom":"Saint-Vallier","code":"26333","codeDepartement":"26","codeRegion":"84","codesPostaux":["26240"],"population":3896},{"nom":"Salettes","code":"26334","codeDepartement":"26","codeRegion":"84","codesPostaux":["26160"],"population":148},{"nom":"Salles-sous-Bois","code":"26335","codeDepartement":"26","codeRegion":"84","codesPostaux":["26770"],"population":187},{"nom":"Saou","code":"26336","codeDepartement":"26","codeRegion":"84","codesPostaux":["26400"],"population":556},{"nom":"Saulce-sur-Rhône","code":"26337","codeDepartement":"26","codeRegion":"84","codesPostaux":["26270"],"population":1850},{"nom":"Sauzet","code":"26338","codeDepartement":"26","codeRegion":"84","codesPostaux":["26740"],"population":1846},{"nom":"Savasse","code":"26339","codeDepartement":"26","codeRegion":"84","codesPostaux":["26740"],"population":1446},{"nom":"Séderon","code":"26340","codeDepartement":"26","codeRegion":"84","codesPostaux":["26560"],"population":267},{"nom":"Serves-sur-Rhône","code":"26341","codeDepartement":"26","codeRegion":"84","codesPostaux":["26600"],"population":743},{"nom":"Solérieux","code":"26342","codeDepartement":"26","codeRegion":"84","codesPostaux":["26130"],"population":342},{"nom":"Souspierre","code":"26343","codeDepartement":"26","codeRegion":"84","codesPostaux":["26160"],"population":97},{"nom":"Soyans","code":"26344","codeDepartement":"26","codeRegion":"84","codesPostaux":["26400"],"population":381},{"nom":"Suze-la-Rousse","code":"26345","codeDepartement":"26","codeRegion":"84","codesPostaux":["26790"],"population":2089},{"nom":"Suze","code":"26346","codeDepartement":"26","codeRegion":"84","codesPostaux":["26400"],"population":234},{"nom":"Tain-l'Hermitage","code":"26347","codeDepartement":"26","codeRegion":"84","codesPostaux":["26600"],"population":6194},{"nom":"Taulignan","code":"26348","codeDepartement":"26","codeRegion":"84","codesPostaux":["26770"],"population":1697},{"nom":"Tersanne","code":"26349","codeDepartement":"26","codeRegion":"84","codesPostaux":["26390"],"population":356},{"nom":"Teyssières","code":"26350","codeDepartement":"26","codeRegion":"84","codesPostaux":["26220"],"population":86},{"nom":"Les Tonils","code":"26351","codeDepartement":"26","codeRegion":"84","codesPostaux":["26460"],"population":21},{"nom":"La Touche","code":"26352","codeDepartement":"26","codeRegion":"84","codesPostaux":["26160"],"population":250},{"nom":"Les Tourrettes","code":"26353","codeDepartement":"26","codeRegion":"84","codesPostaux":["26740"],"population":1035},{"nom":"Triors","code":"26355","codeDepartement":"26","codeRegion":"84","codesPostaux":["26750"],"population":551},{"nom":"Truinas","code":"26356","codeDepartement":"26","codeRegion":"84","codesPostaux":["26460"],"population":122},{"nom":"Tulette","code":"26357","codeDepartement":"26","codeRegion":"84","codesPostaux":["26790"],"population":1976},{"nom":"Upie","code":"26358","codeDepartement":"26","codeRegion":"84","codesPostaux":["26120"],"population":1529},{"nom":"Vachères-en-Quint","code":"26359","codeDepartement":"26","codeRegion":"84","codesPostaux":["26150"],"population":31},{"nom":"Valaurie","code":"26360","codeDepartement":"26","codeRegion":"84","codesPostaux":["26230"],"population":593},{"nom":"Valdrôme","code":"26361","codeDepartement":"26","codeRegion":"84","codesPostaux":["26310"],"population":146},{"nom":"Valence","code":"26362","codeDepartement":"26","codeRegion":"84","codesPostaux":["26000"],"population":62477},{"nom":"Valouse","code":"26363","codeDepartement":"26","codeRegion":"84","codesPostaux":["26110"],"population":34},{"nom":"Vassieux-en-Vercors","code":"26364","codeDepartement":"26","codeRegion":"84","codesPostaux":["26420"],"population":322},{"nom":"Vaunaveys-la-Rochette","code":"26365","codeDepartement":"26","codeRegion":"84","codesPostaux":["26400"],"population":588},{"nom":"Venterol","code":"26367","codeDepartement":"26","codeRegion":"84","codesPostaux":["26110"],"population":705},{"nom":"Vercheny","code":"26368","codeDepartement":"26","codeRegion":"84","codesPostaux":["26340"],"population":450},{"nom":"Verclause","code":"26369","codeDepartement":"26","codeRegion":"84","codesPostaux":["26510"],"population":60},{"nom":"Vercoiran","code":"26370","codeDepartement":"26","codeRegion":"84","codesPostaux":["26170"],"population":142},{"nom":"Véronne","code":"26371","codeDepartement":"26","codeRegion":"84","codesPostaux":["26340"],"population":46},{"nom":"Vers-sur-Méouge","code":"26372","codeDepartement":"26","codeRegion":"84","codesPostaux":["26560"],"population":44},{"nom":"Vesc","code":"26373","codeDepartement":"26","codeRegion":"84","codesPostaux":["26220"],"population":272},{"nom":"Villebois-les-Pins","code":"26374","codeDepartement":"26","codeRegion":"84","codesPostaux":["05700"],"population":19},{"nom":"Villefranche-le-Château","code":"26375","codeDepartement":"26","codeRegion":"84","codesPostaux":["26560"],"population":22},{"nom":"Villeperdrix","code":"26376","codeDepartement":"26","codeRegion":"84","codesPostaux":["26510"],"population":117},{"nom":"Vinsobres","code":"26377","codeDepartement":"26","codeRegion":"84","codesPostaux":["26110"],"population":1165},{"nom":"Volvent","code":"26378","codeDepartement":"26","codeRegion":"84","codesPostaux":["26470"],"population":34},{"nom":"Granges-les-Beaumont","code":"26379","codeDepartement":"26","codeRegion":"84","codesPostaux":["26600"],"population":936},{"nom":"Gervans","code":"26380","codeDepartement":"26","codeRegion":"84","codesPostaux":["26600"],"population":560},{"nom":"Jaillans","code":"26381","codeDepartement":"26","codeRegion":"84","codesPostaux":["26300"],"population":894},{"nom":"Saint-Vincent-la-Commanderie","code":"26382","codeDepartement":"26","codeRegion":"84","codesPostaux":["26300"],"population":527}]